{
  "name": "animals-nature",
  "columns": 8,
  "rows": 16,
  "width": 576,
  "height": 1152,
  "emojiSize": 72,
  "emojis": [
    {
      "emoji": {
        "emoji": "🐵",
        "hexcode": "1F435",
        "group": "animals-nature",
        "subgroups": "animal-mammal",
        "annotation": "monkey face",
        "tags": "face, monkey",
        "openmoji_tags": "jungle, ape, evolution, primate, africa",
        "openmoji_author": "Sofie Ascherl",
        "openmoji_date": "2018-04-18",
        "skintone": "",
        "skintone_combination": "",
        "skintone_base_emoji": "",
        "skintone_base_hexcode": "",
        "unicode": 0.6,
        "order": 2657
      },
      "top": 0,
      "left": 0,
      "index": 0
    },
    {
      "emoji": {
        "emoji": "🐒",
        "hexcode": "1F412",
        "group": "animals-nature",
        "subgroups": "animal-mammal",
        "annotation": "monkey",
        "tags": "monkey",
        "openmoji_tags": "jungle, ape, evolution, primate",
        "openmoji_author": "Sofie Ascherl",
        "openmoji_date": "2018-04-18",
        "skintone": "",
        "skintone_combination": "",
        "skintone_base_emoji": "",
        "skintone_base_hexcode": "",
        "unicode": 0.6,
        "order": 2658
      },
      "top": 0,
      "left": 72,
      "index": 1
    },
    {
      "emoji": {
        "emoji": "🦍",
        "hexcode": "1F98D",
        "group": "animals-nature",
        "subgroups": "animal-mammal",
        "annotation": "gorilla",
        "tags": "gorilla",
        "openmoji_tags": "monkey, primate, evolution",
        "openmoji_author": "Sofie Ascherl",
        "openmoji_date": "2018-04-18",
        "skintone": "",
        "skintone_combination": "",
        "skintone_base_emoji": "",
        "skintone_base_hexcode": "",
        "unicode": 3,
        "order": 2659
      },
      "top": 0,
      "left": 144,
      "index": 2
    },
    {
      "emoji": {
        "emoji": "🦧",
        "hexcode": "1F9A7",
        "group": "animals-nature",
        "subgroups": "animal-mammal",
        "annotation": "orangutan",
        "tags": "ape",
        "openmoji_tags": "",
        "openmoji_author": "Yasmin Abdullahi",
        "openmoji_date": "2019-05-07",
        "skintone": "",
        "skintone_combination": "",
        "skintone_base_emoji": "",
        "skintone_base_hexcode": "",
        "unicode": 12,
        "order": 2660
      },
      "top": 0,
      "left": 216,
      "index": 3
    },
    {
      "emoji": {
        "emoji": "🐶",
        "hexcode": "1F436",
        "group": "animals-nature",
        "subgroups": "animal-mammal",
        "annotation": "dog face",
        "tags": "dog, face, pet",
        "openmoji_tags": "friend, puppy, doggy",
        "openmoji_author": "Sofie Ascherl",
        "openmoji_date": "2018-04-18",
        "skintone": "",
        "skintone_combination": "",
        "skintone_base_emoji": "",
        "skintone_base_hexcode": "",
        "unicode": 0.6,
        "order": 2661
      },
      "top": 0,
      "left": 288,
      "index": 4
    },
    {
      "emoji": {
        "emoji": "🐕️",
        "hexcode": "1F415",
        "group": "animals-nature",
        "subgroups": "animal-mammal",
        "annotation": "dog",
        "tags": "pet",
        "openmoji_tags": "puppy, doggy",
        "openmoji_author": "Sofie Ascherl",
        "openmoji_date": "2018-04-18",
        "skintone": "",
        "skintone_combination": "",
        "skintone_base_emoji": "",
        "skintone_base_hexcode": "",
        "unicode": 0.7,
        "order": 2662
      },
      "top": 0,
      "left": 360,
      "index": 5
    },
    {
      "emoji": {
        "emoji": "🦮",
        "hexcode": "1F9AE",
        "group": "animals-nature",
        "subgroups": "animal-mammal",
        "annotation": "guide dog",
        "tags": "accessibility, blind, guide",
        "openmoji_tags": "",
        "openmoji_author": "Yasmin Abdullahi",
        "openmoji_date": "2019-05-07",
        "skintone": "",
        "skintone_combination": "",
        "skintone_base_emoji": "",
        "skintone_base_hexcode": "",
        "unicode": 12,
        "order": 2663
      },
      "top": 0,
      "left": 432,
      "index": 6
    },
    {
      "emoji": {
        "emoji": "🐩",
        "hexcode": "1F429",
        "group": "animals-nature",
        "subgroups": "animal-mammal",
        "annotation": "poodle",
        "tags": "dog",
        "openmoji_tags": "",
        "openmoji_author": "Anne Frauendorf",
        "openmoji_date": "2018-11-16",
        "skintone": "",
        "skintone_combination": "",
        "skintone_base_emoji": "",
        "skintone_base_hexcode": "",
        "unicode": 0.6,
        "order": 2665
      },
      "top": 0,
      "left": 504,
      "index": 7
    },
    {
      "emoji": {
        "emoji": "🐺",
        "hexcode": "1F43A",
        "group": "animals-nature",
        "subgroups": "animal-mammal",
        "annotation": "wolf",
        "tags": "face",
        "openmoji_tags": "pack, wild, free, forest, dog",
        "openmoji_author": "Sofie Ascherl",
        "openmoji_date": "2018-04-18",
        "skintone": "",
        "skintone_combination": "",
        "skintone_base_emoji": "",
        "skintone_base_hexcode": "",
        "unicode": 0.6,
        "order": 2666
      },
      "top": 72,
      "left": 0,
      "index": 8
    },
    {
      "emoji": {
        "emoji": "🦊",
        "hexcode": "1F98A",
        "group": "animals-nature",
        "subgroups": "animal-mammal",
        "annotation": "fox",
        "tags": "face",
        "openmoji_tags": "smart, red, quick, intelligent",
        "openmoji_author": "Sofie Ascherl",
        "openmoji_date": "2018-04-18",
        "skintone": "",
        "skintone_combination": "",
        "skintone_base_emoji": "",
        "skintone_base_hexcode": "",
        "unicode": 3,
        "order": 2667
      },
      "top": 72,
      "left": 72,
      "index": 9
    },
    {
      "emoji": {
        "emoji": "🦝",
        "hexcode": "1F99D",
        "group": "animals-nature",
        "subgroups": "animal-mammal",
        "annotation": "raccoon",
        "tags": "curious, sly",
        "openmoji_tags": "",
        "openmoji_author": "Laura Schießer",
        "openmoji_date": "2019-05-06",
        "skintone": "",
        "skintone_combination": "",
        "skintone_base_emoji": "",
        "skintone_base_hexcode": "",
        "unicode": 11,
        "order": 2668
      },
      "top": 72,
      "left": 144,
      "index": 10
    },
    {
      "emoji": {
        "emoji": "🐱",
        "hexcode": "1F431",
        "group": "animals-nature",
        "subgroups": "animal-mammal",
        "annotation": "cat face",
        "tags": "cat, face, pet",
        "openmoji_tags": "pet, kitty, kitten, miau",
        "openmoji_author": "Sofie Ascherl",
        "openmoji_date": "2018-04-18",
        "skintone": "",
        "skintone_combination": "",
        "skintone_base_emoji": "",
        "skintone_base_hexcode": "",
        "unicode": 0.6,
        "order": 2669
      },
      "top": 72,
      "left": 216,
      "index": 11
    },
    {
      "emoji": {
        "emoji": "🐈️",
        "hexcode": "1F408",
        "group": "animals-nature",
        "subgroups": "animal-mammal",
        "annotation": "cat",
        "tags": "pet",
        "openmoji_tags": "pet, kitty, kitten, miau",
        "openmoji_author": "Sofie Ascherl",
        "openmoji_date": "2018-04-18",
        "skintone": "",
        "skintone_combination": "",
        "skintone_base_emoji": "",
        "skintone_base_hexcode": "",
        "unicode": 0.7,
        "order": 2670
      },
      "top": 72,
      "left": 288,
      "index": 12
    },
    {
      "emoji": {
        "emoji": "🦁",
        "hexcode": "1F981",
        "group": "animals-nature",
        "subgroups": "animal-mammal",
        "annotation": "lion",
        "tags": "face, leo, zodiac",
        "openmoji_tags": "king, simba, royal, wild, cat",
        "openmoji_author": "Sofie Ascherl",
        "openmoji_date": "2018-04-18",
        "skintone": "",
        "skintone_combination": "",
        "skintone_base_emoji": "",
        "skintone_base_hexcode": "",
        "unicode": 1,
        "order": 2672
      },
      "top": 72,
      "left": 360,
      "index": 13
    },
    {
      "emoji": {
        "emoji": "🐯",
        "hexcode": "1F42F",
        "group": "animals-nature",
        "subgroups": "animal-mammal",
        "annotation": "tiger face",
        "tags": "face, tiger",
        "openmoji_tags": "stripes, strong, cat, wild",
        "openmoji_author": "Sofie Ascherl",
        "openmoji_date": "2018-04-18",
        "skintone": "",
        "skintone_combination": "",
        "skintone_base_emoji": "",
        "skintone_base_hexcode": "",
        "unicode": 0.6,
        "order": 2673
      },
      "top": 72,
      "left": 432,
      "index": 14
    },
    {
      "emoji": {
        "emoji": "🐅",
        "hexcode": "1F405",
        "group": "animals-nature",
        "subgroups": "animal-mammal",
        "annotation": "tiger",
        "tags": "tiger",
        "openmoji_tags": "stripes, strong, cat, wild",
        "openmoji_author": "Sofie Ascherl",
        "openmoji_date": "2018-04-18",
        "skintone": "",
        "skintone_combination": "",
        "skintone_base_emoji": "",
        "skintone_base_hexcode": "",
        "unicode": 1,
        "order": 2674
      },
      "top": 72,
      "left": 504,
      "index": 15
    },
    {
      "emoji": {
        "emoji": "🐆",
        "hexcode": "1F406",
        "group": "animals-nature",
        "subgroups": "animal-mammal",
        "annotation": "leopard",
        "tags": "leopard",
        "openmoji_tags": "dots, strong, cat, wild, spots",
        "openmoji_author": "Sofie Ascherl",
        "openmoji_date": "2018-04-18",
        "skintone": "",
        "skintone_combination": "",
        "skintone_base_emoji": "",
        "skintone_base_hexcode": "",
        "unicode": 1,
        "order": 2675
      },
      "top": 144,
      "left": 0,
      "index": 16
    },
    {
      "emoji": {
        "emoji": "🐴",
        "hexcode": "1F434",
        "group": "animals-nature",
        "subgroups": "animal-mammal",
        "annotation": "horse face",
        "tags": "face, horse",
        "openmoji_tags": "riding, sport",
        "openmoji_author": "Sofie Ascherl",
        "openmoji_date": "2018-04-18",
        "skintone": "",
        "skintone_combination": "",
        "skintone_base_emoji": "",
        "skintone_base_hexcode": "",
        "unicode": 0.6,
        "order": 2676
      },
      "top": 144,
      "left": 72,
      "index": 17
    },
    {
      "emoji": {
        "emoji": "🐎",
        "hexcode": "1F40E",
        "group": "animals-nature",
        "subgroups": "animal-mammal",
        "annotation": "horse",
        "tags": "equestrian, racehorse, racing",
        "openmoji_tags": "riding, sport",
        "openmoji_author": "Sofie Ascherl",
        "openmoji_date": "2018-04-18",
        "skintone": "",
        "skintone_combination": "",
        "skintone_base_emoji": "",
        "skintone_base_hexcode": "",
        "unicode": 0.6,
        "order": 2677
      },
      "top": 144,
      "left": 144,
      "index": 18
    },
    {
      "emoji": {
        "emoji": "🦄",
        "hexcode": "1F984",
        "group": "animals-nature",
        "subgroups": "animal-mammal",
        "annotation": "unicorn",
        "tags": "face",
        "openmoji_tags": "fabulous, magical, rainbow, schwäbisch, gmünd",
        "openmoji_author": "Sofie Ascherl",
        "openmoji_date": "2018-04-18",
        "skintone": "",
        "skintone_combination": "",
        "skintone_base_emoji": "",
        "skintone_base_hexcode": "",
        "unicode": 1,
        "order": 2678
      },
      "top": 144,
      "left": 216,
      "index": 19
    },
    {
      "emoji": {
        "emoji": "🦓",
        "hexcode": "1F993",
        "group": "animals-nature",
        "subgroups": "animal-mammal",
        "annotation": "zebra",
        "tags": "stripe",
        "openmoji_tags": "horse, black, white",
        "openmoji_author": "Sofie Ascherl",
        "openmoji_date": "2018-04-18",
        "skintone": "",
        "skintone_combination": "",
        "skintone_base_emoji": "",
        "skintone_base_hexcode": "",
        "unicode": 5,
        "order": 2679
      },
      "top": 144,
      "left": 288,
      "index": 20
    },
    {
      "emoji": {
        "emoji": "🦌",
        "hexcode": "1F98C",
        "group": "animals-nature",
        "subgroups": "animal-mammal",
        "annotation": "deer",
        "tags": "deer",
        "openmoji_tags": "forest, hunt, antler",
        "openmoji_author": "Sofie Ascherl",
        "openmoji_date": "2018-04-18",
        "skintone": "",
        "skintone_combination": "",
        "skintone_base_emoji": "",
        "skintone_base_hexcode": "",
        "unicode": 3,
        "order": 2680
      },
      "top": 144,
      "left": 360,
      "index": 21
    },
    {
      "emoji": {
        "emoji": "🐮",
        "hexcode": "1F42E",
        "group": "animals-nature",
        "subgroups": "animal-mammal",
        "annotation": "cow face",
        "tags": "cow, face",
        "openmoji_tags": "farm, milk, beef, grass, dairy, horns, cheese",
        "openmoji_author": "Sofie Ascherl",
        "openmoji_date": "2018-04-18",
        "skintone": "",
        "skintone_combination": "",
        "skintone_base_emoji": "",
        "skintone_base_hexcode": "",
        "unicode": 0.6,
        "order": 2682
      },
      "top": 144,
      "left": 432,
      "index": 22
    },
    {
      "emoji": {
        "emoji": "🐂",
        "hexcode": "1F402",
        "group": "animals-nature",
        "subgroups": "animal-mammal",
        "annotation": "ox",
        "tags": "bull, taurus, zodiac",
        "openmoji_tags": "strong, farm, acre, horns, beef",
        "openmoji_author": "Sofie Ascherl",
        "openmoji_date": "2018-04-18",
        "skintone": "",
        "skintone_combination": "",
        "skintone_base_emoji": "",
        "skintone_base_hexcode": "",
        "unicode": 1,
        "order": 2683
      },
      "top": 144,
      "left": 504,
      "index": 23
    },
    {
      "emoji": {
        "emoji": "🐃",
        "hexcode": "1F403",
        "group": "animals-nature",
        "subgroups": "animal-mammal",
        "annotation": "water buffalo",
        "tags": "buffalo, water",
        "openmoji_tags": "black, horns, beef",
        "openmoji_author": "Sofie Ascherl",
        "openmoji_date": "2018-04-18",
        "skintone": "",
        "skintone_combination": "",
        "skintone_base_emoji": "",
        "skintone_base_hexcode": "",
        "unicode": 1,
        "order": 2684
      },
      "top": 216,
      "left": 0,
      "index": 24
    },
    {
      "emoji": {
        "emoji": "🐄",
        "hexcode": "1F404",
        "group": "animals-nature",
        "subgroups": "animal-mammal",
        "annotation": "cow",
        "tags": "cow",
        "openmoji_tags": "farm, milk, beef, grass, dairy, horns, cheese",
        "openmoji_author": "Sofie Ascherl",
        "openmoji_date": "2018-04-18",
        "skintone": "",
        "skintone_combination": "",
        "skintone_base_emoji": "",
        "skintone_base_hexcode": "",
        "unicode": 1,
        "order": 2685
      },
      "top": 216,
      "left": 72,
      "index": 25
    },
    {
      "emoji": {
        "emoji": "🐷",
        "hexcode": "1F437",
        "group": "animals-nature",
        "subgroups": "animal-mammal",
        "annotation": "pig face",
        "tags": "face, pig",
        "openmoji_tags": "pork, farm, pink, meat, oink",
        "openmoji_author": "Sofie Ascherl",
        "openmoji_date": "2018-04-18",
        "skintone": "",
        "skintone_combination": "",
        "skintone_base_emoji": "",
        "skintone_base_hexcode": "",
        "unicode": 0.6,
        "order": 2686
      },
      "top": 216,
      "left": 144,
      "index": 26
    },
    {
      "emoji": {
        "emoji": "🐖",
        "hexcode": "1F416",
        "group": "animals-nature",
        "subgroups": "animal-mammal",
        "annotation": "pig",
        "tags": "sow",
        "openmoji_tags": "pork, farm, pink, meat, oink",
        "openmoji_author": "Sofie Ascherl",
        "openmoji_date": "2018-04-18",
        "skintone": "",
        "skintone_combination": "",
        "skintone_base_emoji": "",
        "skintone_base_hexcode": "",
        "unicode": 1,
        "order": 2687
      },
      "top": 216,
      "left": 216,
      "index": 27
    },
    {
      "emoji": {
        "emoji": "🐗",
        "hexcode": "1F417",
        "group": "animals-nature",
        "subgroups": "animal-mammal",
        "annotation": "boar",
        "tags": "pig",
        "openmoji_tags": "wild, strong, forest, angry, teeth, tusk",
        "openmoji_author": "Sofie Ascherl",
        "openmoji_date": "2018-04-18",
        "skintone": "",
        "skintone_combination": "",
        "skintone_base_emoji": "",
        "skintone_base_hexcode": "",
        "unicode": 0.6,
        "order": 2688
      },
      "top": 216,
      "left": 288,
      "index": 28
    },
    {
      "emoji": {
        "emoji": "🐽",
        "hexcode": "1F43D",
        "group": "animals-nature",
        "subgroups": "animal-mammal",
        "annotation": "pig nose",
        "tags": "face, nose, pig",
        "openmoji_tags": "smell, socket, nose",
        "openmoji_author": "Sofie Ascherl",
        "openmoji_date": "2018-04-18",
        "skintone": "",
        "skintone_combination": "",
        "skintone_base_emoji": "",
        "skintone_base_hexcode": "",
        "unicode": 0.6,
        "order": 2689
      },
      "top": 216,
      "left": 360,
      "index": 29
    },
    {
      "emoji": {
        "emoji": "🐏",
        "hexcode": "1F40F",
        "group": "animals-nature",
        "subgroups": "animal-mammal",
        "annotation": "ram",
        "tags": "aries, male, sheep, zodiac",
        "openmoji_tags": "horns, grass, hooves, wool",
        "openmoji_author": "Sofie Ascherl",
        "openmoji_date": "2018-04-18",
        "skintone": "",
        "skintone_combination": "",
        "skintone_base_emoji": "",
        "skintone_base_hexcode": "",
        "unicode": 1,
        "order": 2690
      },
      "top": 216,
      "left": 432,
      "index": 30
    },
    {
      "emoji": {
        "emoji": "🐑",
        "hexcode": "1F411",
        "group": "animals-nature",
        "subgroups": "animal-mammal",
        "annotation": "ewe",
        "tags": "female, sheep",
        "openmoji_tags": "horns, grass, hooves, wool, farm",
        "openmoji_author": "Sofie Ascherl",
        "openmoji_date": "2018-04-18",
        "skintone": "",
        "skintone_combination": "",
        "skintone_base_emoji": "",
        "skintone_base_hexcode": "",
        "unicode": 0.6,
        "order": 2691
      },
      "top": 216,
      "left": 504,
      "index": 31
    },
    {
      "emoji": {
        "emoji": "🐐",
        "hexcode": "1F410",
        "group": "animals-nature",
        "subgroups": "animal-mammal",
        "annotation": "goat",
        "tags": "capricorn, zodiac",
        "openmoji_tags": "horns, farm, milk, cheese",
        "openmoji_author": "Sofie Ascherl",
        "openmoji_date": "2018-04-18",
        "skintone": "",
        "skintone_combination": "",
        "skintone_base_emoji": "",
        "skintone_base_hexcode": "",
        "unicode": 1,
        "order": 2692
      },
      "top": 288,
      "left": 0,
      "index": 32
    },
    {
      "emoji": {
        "emoji": "🐪",
        "hexcode": "1F42A",
        "group": "animals-nature",
        "subgroups": "animal-mammal",
        "annotation": "camel",
        "tags": "dromedary, hump",
        "openmoji_tags": "desert, oasis, sahara, sun, hot, hump",
        "openmoji_author": "Sofie Ascherl",
        "openmoji_date": "2018-04-18",
        "skintone": "",
        "skintone_combination": "",
        "skintone_base_emoji": "",
        "skintone_base_hexcode": "",
        "unicode": 1,
        "order": 2693
      },
      "top": 288,
      "left": 72,
      "index": 33
    },
    {
      "emoji": {
        "emoji": "🐫",
        "hexcode": "1F42B",
        "group": "animals-nature",
        "subgroups": "animal-mammal",
        "annotation": "two-hump camel",
        "tags": "bactrian, camel, hump",
        "openmoji_tags": "desert, oasis, sahara, sun, hot, hump",
        "openmoji_author": "Sofie Ascherl",
        "openmoji_date": "2018-04-18",
        "skintone": "",
        "skintone_combination": "",
        "skintone_base_emoji": "",
        "skintone_base_hexcode": "",
        "unicode": 0.6,
        "order": 2694
      },
      "top": 288,
      "left": 144,
      "index": 34
    },
    {
      "emoji": {
        "emoji": "🦙",
        "hexcode": "1F999",
        "group": "animals-nature",
        "subgroups": "animal-mammal",
        "annotation": "llama",
        "tags": "alpaca, guanaco, vicuña, wool",
        "openmoji_tags": "",
        "openmoji_author": "Carlin MacKenzie",
        "openmoji_date": "2020-03-21",
        "skintone": "",
        "skintone_combination": "",
        "skintone_base_emoji": "",
        "skintone_base_hexcode": "",
        "unicode": 11,
        "order": 2695
      },
      "top": 288,
      "left": 216,
      "index": 35
    },
    {
      "emoji": {
        "emoji": "🦒",
        "hexcode": "1F992",
        "group": "animals-nature",
        "subgroups": "animal-mammal",
        "annotation": "giraffe",
        "tags": "spots",
        "openmoji_tags": "long, neck, trees, big",
        "openmoji_author": "Sofie Ascherl",
        "openmoji_date": "2018-04-18",
        "skintone": "",
        "skintone_combination": "",
        "skintone_base_emoji": "",
        "skintone_base_hexcode": "",
        "unicode": 5,
        "order": 2696
      },
      "top": 288,
      "left": 288,
      "index": 36
    },
    {
      "emoji": {
        "emoji": "🐘",
        "hexcode": "1F418",
        "group": "animals-nature",
        "subgroups": "animal-mammal",
        "annotation": "elephant",
        "tags": "elephant",
        "openmoji_tags": "big, wrinkles, trunk, töröö",
        "openmoji_author": "Sofie Ascherl",
        "openmoji_date": "2018-04-18",
        "skintone": "",
        "skintone_combination": "",
        "skintone_base_emoji": "",
        "skintone_base_hexcode": "",
        "unicode": 0.6,
        "order": 2697
      },
      "top": 288,
      "left": 360,
      "index": 37
    },
    {
      "emoji": {
        "emoji": "🦏",
        "hexcode": "1F98F",
        "group": "animals-nature",
        "subgroups": "animal-mammal",
        "annotation": "rhinoceros",
        "tags": "rhinoceros",
        "openmoji_tags": "rhino, horn, africa",
        "openmoji_author": "Sofie Ascherl",
        "openmoji_date": "2018-04-18",
        "skintone": "",
        "skintone_combination": "",
        "skintone_base_emoji": "",
        "skintone_base_hexcode": "",
        "unicode": 3,
        "order": 2699
      },
      "top": 288,
      "left": 432,
      "index": 38
    },
    {
      "emoji": {
        "emoji": "🦛",
        "hexcode": "1F99B",
        "group": "animals-nature",
        "subgroups": "animal-mammal",
        "annotation": "hippopotamus",
        "tags": "hippo",
        "openmoji_tags": "",
        "openmoji_author": "Laura Schießer",
        "openmoji_date": "2019-05-06",
        "skintone": "",
        "skintone_combination": "",
        "skintone_base_emoji": "",
        "skintone_base_hexcode": "",
        "unicode": 11,
        "order": 2700
      },
      "top": 288,
      "left": 504,
      "index": 39
    },
    {
      "emoji": {
        "emoji": "🐭",
        "hexcode": "1F42D",
        "group": "animals-nature",
        "subgroups": "animal-mammal",
        "annotation": "mouse face",
        "tags": "face, mouse",
        "openmoji_tags": "cute, whiskers, tiny, rodent",
        "openmoji_author": "Sofie Ascherl",
        "openmoji_date": "2018-04-18",
        "skintone": "",
        "skintone_combination": "",
        "skintone_base_emoji": "",
        "skintone_base_hexcode": "",
        "unicode": 0.6,
        "order": 2701
      },
      "top": 360,
      "left": 0,
      "index": 40
    },
    {
      "emoji": {
        "emoji": "🐁",
        "hexcode": "1F401",
        "group": "animals-nature",
        "subgroups": "animal-mammal",
        "annotation": "mouse",
        "tags": "mouse",
        "openmoji_tags": "small, cute, whiskers, tiny, rodent",
        "openmoji_author": "Sofie Ascherl",
        "openmoji_date": "2018-04-18",
        "skintone": "",
        "skintone_combination": "",
        "skintone_base_emoji": "",
        "skintone_base_hexcode": "",
        "unicode": 1,
        "order": 2702
      },
      "top": 360,
      "left": 72,
      "index": 41
    },
    {
      "emoji": {
        "emoji": "🐀",
        "hexcode": "1F400",
        "group": "animals-nature",
        "subgroups": "animal-mammal",
        "annotation": "rat",
        "tags": "rat",
        "openmoji_tags": "rodent, plaque, fleas, canal, garbage",
        "openmoji_author": "Sofie Ascherl",
        "openmoji_date": "2018-04-18",
        "skintone": "",
        "skintone_combination": "",
        "skintone_base_emoji": "",
        "skintone_base_hexcode": "",
        "unicode": 1,
        "order": 2703
      },
      "top": 360,
      "left": 144,
      "index": 42
    },
    {
      "emoji": {
        "emoji": "🐹",
        "hexcode": "1F439",
        "group": "animals-nature",
        "subgroups": "animal-mammal",
        "annotation": "hamster",
        "tags": "face, pet",
        "openmoji_tags": "rodent, fat, fluffy, corn",
        "openmoji_author": "Sofie Ascherl",
        "openmoji_date": "2018-04-18",
        "skintone": "",
        "skintone_combination": "",
        "skintone_base_emoji": "",
        "skintone_base_hexcode": "",
        "unicode": 0.6,
        "order": 2704
      },
      "top": 360,
      "left": 216,
      "index": 43
    },
    {
      "emoji": {
        "emoji": "🐰",
        "hexcode": "1F430",
        "group": "animals-nature",
        "subgroups": "animal-mammal",
        "annotation": "rabbit face",
        "tags": "bunny, face, pet, rabbit",
        "openmoji_tags": "rodent, teeth, cute, ears, bunny, hopping, easter",
        "openmoji_author": "Sofie Ascherl",
        "openmoji_date": "2018-04-18",
        "skintone": "",
        "skintone_combination": "",
        "skintone_base_emoji": "",
        "skintone_base_hexcode": "",
        "unicode": 0.6,
        "order": 2705
      },
      "top": 360,
      "left": 288,
      "index": 44
    },
    {
      "emoji": {
        "emoji": "🐇",
        "hexcode": "1F407",
        "group": "animals-nature",
        "subgroups": "animal-mammal",
        "annotation": "rabbit",
        "tags": "bunny, pet",
        "openmoji_tags": "rodent, teeth, cute, ears, bunny, hopping, easter",
        "openmoji_author": "Sofie Ascherl",
        "openmoji_date": "2018-04-18",
        "skintone": "",
        "skintone_combination": "",
        "skintone_base_emoji": "",
        "skintone_base_hexcode": "",
        "unicode": 1,
        "order": 2706
      },
      "top": 360,
      "left": 360,
      "index": 45
    },
    {
      "emoji": {
        "emoji": "🐿️",
        "hexcode": "1F43F",
        "group": "animals-nature",
        "subgroups": "animal-mammal",
        "annotation": "chipmunk",
        "tags": "squirrel",
        "openmoji_tags": "squirrel, alvin",
        "openmoji_author": "Sofie Ascherl",
        "openmoji_date": "2018-04-18",
        "skintone": "",
        "skintone_combination": "",
        "skintone_base_emoji": "",
        "skintone_base_hexcode": "",
        "unicode": 0.7,
        "order": 2708
      },
      "top": 360,
      "left": 432,
      "index": 46
    },
    {
      "emoji": {
        "emoji": "🦔",
        "hexcode": "1F994",
        "group": "animals-nature",
        "subgroups": "animal-mammal",
        "annotation": "hedgehog",
        "tags": "spiny",
        "openmoji_tags": "prickly, fall, apple, leafs",
        "openmoji_author": "Sofie Ascherl",
        "openmoji_date": "2018-04-18",
        "skintone": "",
        "skintone_combination": "",
        "skintone_base_emoji": "",
        "skintone_base_hexcode": "",
        "unicode": 5,
        "order": 2710
      },
      "top": 360,
      "left": 504,
      "index": 47
    },
    {
      "emoji": {
        "emoji": "🦇",
        "hexcode": "1F987",
        "group": "animals-nature",
        "subgroups": "animal-mammal",
        "annotation": "bat",
        "tags": "vampire",
        "openmoji_tags": "batman, dracula",
        "openmoji_author": "Sofie Ascherl",
        "openmoji_date": "2018-04-18",
        "skintone": "",
        "skintone_combination": "",
        "skintone_base_emoji": "",
        "skintone_base_hexcode": "",
        "unicode": 3,
        "order": 2711
      },
      "top": 432,
      "left": 0,
      "index": 48
    },
    {
      "emoji": {
        "emoji": "🐻",
        "hexcode": "1F43B",
        "group": "animals-nature",
        "subgroups": "animal-mammal",
        "annotation": "bear",
        "tags": "face",
        "openmoji_tags": "brown, salmon, river, thick",
        "openmoji_author": "Sofie Ascherl",
        "openmoji_date": "2018-04-18",
        "skintone": "",
        "skintone_combination": "",
        "skintone_base_emoji": "",
        "skintone_base_hexcode": "",
        "unicode": 0.6,
        "order": 2712
      },
      "top": 432,
      "left": 72,
      "index": 49
    },
    {
      "emoji": {
        "emoji": "🐨",
        "hexcode": "1F428",
        "group": "animals-nature",
        "subgroups": "animal-mammal",
        "annotation": "koala",
        "tags": "bear",
        "openmoji_tags": "grey, fluffy, eucalyptus, australia, clingy",
        "openmoji_author": "Sofie Ascherl",
        "openmoji_date": "2018-04-18",
        "skintone": "",
        "skintone_combination": "",
        "skintone_base_emoji": "",
        "skintone_base_hexcode": "",
        "unicode": 0.6,
        "order": 2715
      },
      "top": 432,
      "left": 144,
      "index": 50
    },
    {
      "emoji": {
        "emoji": "🐼",
        "hexcode": "1F43C",
        "group": "animals-nature",
        "subgroups": "animal-mammal",
        "annotation": "panda",
        "tags": "face",
        "openmoji_tags": "kawaii, cute, japan",
        "openmoji_author": "Sofie Ascherl",
        "openmoji_date": "2018-04-18",
        "skintone": "",
        "skintone_combination": "",
        "skintone_base_emoji": "",
        "skintone_base_hexcode": "",
        "unicode": 0.6,
        "order": 2716
      },
      "top": 432,
      "left": 216,
      "index": 51
    },
    {
      "emoji": {
        "emoji": "🦥",
        "hexcode": "1F9A5",
        "group": "animals-nature",
        "subgroups": "animal-mammal",
        "annotation": "sloth",
        "tags": "lazy, slow",
        "openmoji_tags": "",
        "openmoji_author": "Yasmin Abdullahi",
        "openmoji_date": "2019-05-07",
        "skintone": "",
        "skintone_combination": "",
        "skintone_base_emoji": "",
        "skintone_base_hexcode": "",
        "unicode": 12,
        "order": 2717
      },
      "top": 432,
      "left": 288,
      "index": 52
    },
    {
      "emoji": {
        "emoji": "🦦",
        "hexcode": "1F9A6",
        "group": "animals-nature",
        "subgroups": "animal-mammal",
        "annotation": "otter",
        "tags": "fishing, playful",
        "openmoji_tags": "",
        "openmoji_author": "Yasmin Abdullahi",
        "openmoji_date": "2019-05-07",
        "skintone": "",
        "skintone_combination": "",
        "skintone_base_emoji": "",
        "skintone_base_hexcode": "",
        "unicode": 12,
        "order": 2718
      },
      "top": 432,
      "left": 360,
      "index": 53
    },
    {
      "emoji": {
        "emoji": "🦨",
        "hexcode": "1F9A8",
        "group": "animals-nature",
        "subgroups": "animal-mammal",
        "annotation": "skunk",
        "tags": "stink",
        "openmoji_tags": "",
        "openmoji_author": "Yasmin Abdullahi",
        "openmoji_date": "2019-05-07",
        "skintone": "",
        "skintone_combination": "",
        "skintone_base_emoji": "",
        "skintone_base_hexcode": "",
        "unicode": 12,
        "order": 2719
      },
      "top": 432,
      "left": 432,
      "index": 54
    },
    {
      "emoji": {
        "emoji": "🦘",
        "hexcode": "1F998",
        "group": "animals-nature",
        "subgroups": "animal-mammal",
        "annotation": "kangaroo",
        "tags": "australia, joey, jump, marsupial",
        "openmoji_tags": "",
        "openmoji_author": "Laura Schießer",
        "openmoji_date": "2019-05-06",
        "skintone": "",
        "skintone_combination": "",
        "skintone_base_emoji": "",
        "skintone_base_hexcode": "",
        "unicode": 11,
        "order": 2720
      },
      "top": 432,
      "left": 504,
      "index": 55
    },
    {
      "emoji": {
        "emoji": "🦡",
        "hexcode": "1F9A1",
        "group": "animals-nature",
        "subgroups": "animal-mammal",
        "annotation": "badger",
        "tags": "honey badger, pester",
        "openmoji_tags": "",
        "openmoji_author": "Laura Schießer",
        "openmoji_date": "2019-05-07",
        "skintone": "",
        "skintone_combination": "",
        "skintone_base_emoji": "",
        "skintone_base_hexcode": "",
        "unicode": 11,
        "order": 2721
      },
      "top": 504,
      "left": 0,
      "index": 56
    },
    {
      "emoji": {
        "emoji": "🐾",
        "hexcode": "1F43E",
        "group": "animals-nature",
        "subgroups": "animal-mammal",
        "annotation": "paw prints",
        "tags": "feet, paw, print",
        "openmoji_tags": "paws, feet, pet, animal",
        "openmoji_author": "Sofie Ascherl",
        "openmoji_date": "2018-04-18",
        "skintone": "",
        "skintone_combination": "",
        "skintone_base_emoji": "",
        "skintone_base_hexcode": "",
        "unicode": 0.6,
        "order": 2722
      },
      "top": 504,
      "left": 72,
      "index": 57
    },
    {
      "emoji": {
        "emoji": "🦃",
        "hexcode": "1F983",
        "group": "animals-nature",
        "subgroups": "animal-bird",
        "annotation": "turkey",
        "tags": "bird",
        "openmoji_tags": "",
        "openmoji_author": "Selina Bauder",
        "openmoji_date": "2018-04-18",
        "skintone": "",
        "skintone_combination": "",
        "skintone_base_emoji": "",
        "skintone_base_hexcode": "",
        "unicode": 1,
        "order": 2723
      },
      "top": 504,
      "left": 144,
      "index": 58
    },
    {
      "emoji": {
        "emoji": "🐔",
        "hexcode": "1F414",
        "group": "animals-nature",
        "subgroups": "animal-bird",
        "annotation": "chicken",
        "tags": "bird",
        "openmoji_tags": "egg",
        "openmoji_author": "Selina Bauder",
        "openmoji_date": "2018-04-18",
        "skintone": "",
        "skintone_combination": "",
        "skintone_base_emoji": "",
        "skintone_base_hexcode": "",
        "unicode": 0.6,
        "order": 2724
      },
      "top": 504,
      "left": 216,
      "index": 59
    },
    {
      "emoji": {
        "emoji": "🐓",
        "hexcode": "1F413",
        "group": "animals-nature",
        "subgroups": "animal-bird",
        "annotation": "rooster",
        "tags": "bird",
        "openmoji_tags": "egg",
        "openmoji_author": "Selina Bauder",
        "openmoji_date": "2018-04-18",
        "skintone": "",
        "skintone_combination": "",
        "skintone_base_emoji": "",
        "skintone_base_hexcode": "",
        "unicode": 1,
        "order": 2725
      },
      "top": 504,
      "left": 288,
      "index": 60
    },
    {
      "emoji": {
        "emoji": "🐣",
        "hexcode": "1F423",
        "group": "animals-nature",
        "subgroups": "animal-bird",
        "annotation": "hatching chick",
        "tags": "baby, bird, chick, hatching",
        "openmoji_tags": "baby, egg",
        "openmoji_author": "Selina Bauder",
        "openmoji_date": "2018-04-18",
        "skintone": "",
        "skintone_combination": "",
        "skintone_base_emoji": "",
        "skintone_base_hexcode": "",
        "unicode": 0.6,
        "order": 2726
      },
      "top": 504,
      "left": 360,
      "index": 61
    },
    {
      "emoji": {
        "emoji": "🐤",
        "hexcode": "1F424",
        "group": "animals-nature",
        "subgroups": "animal-bird",
        "annotation": "baby chick",
        "tags": "baby, bird, chick",
        "openmoji_tags": "small, baby, egg",
        "openmoji_author": "Selina Bauder",
        "openmoji_date": "2018-04-18",
        "skintone": "",
        "skintone_combination": "",
        "skintone_base_emoji": "",
        "skintone_base_hexcode": "",
        "unicode": 0.6,
        "order": 2727
      },
      "top": 504,
      "left": 432,
      "index": 62
    },
    {
      "emoji": {
        "emoji": "🐥",
        "hexcode": "1F425",
        "group": "animals-nature",
        "subgroups": "animal-bird",
        "annotation": "front-facing baby chick",
        "tags": "baby, bird, chick",
        "openmoji_tags": "",
        "openmoji_author": "Selina Bauder",
        "openmoji_date": "2018-04-18",
        "skintone": "",
        "skintone_combination": "",
        "skintone_base_emoji": "",
        "skintone_base_hexcode": "",
        "unicode": 0.6,
        "order": 2728
      },
      "top": 504,
      "left": 504,
      "index": 63
    },
    {
      "emoji": {
        "emoji": "🐦️",
        "hexcode": "1F426",
        "group": "animals-nature",
        "subgroups": "animal-bird",
        "annotation": "bird",
        "tags": "bird",
        "openmoji_tags": "fly, colourful",
        "openmoji_author": "Selina Bauder",
        "openmoji_date": "2018-04-18",
        "skintone": "",
        "skintone_combination": "",
        "skintone_base_emoji": "",
        "skintone_base_hexcode": "",
        "unicode": 0.6,
        "order": 2729
      },
      "top": 576,
      "left": 0,
      "index": 64
    },
    {
      "emoji": {
        "emoji": "🐧",
        "hexcode": "1F427",
        "group": "animals-nature",
        "subgroups": "animal-bird",
        "annotation": "penguin",
        "tags": "bird",
        "openmoji_tags": "",
        "openmoji_author": "Selina Bauder",
        "openmoji_date": "2018-04-18",
        "skintone": "",
        "skintone_combination": "",
        "skintone_base_emoji": "",
        "skintone_base_hexcode": "",
        "unicode": 0.6,
        "order": 2730
      },
      "top": 576,
      "left": 72,
      "index": 65
    },
    {
      "emoji": {
        "emoji": "🕊️",
        "hexcode": "1F54A",
        "group": "animals-nature",
        "subgroups": "animal-bird",
        "annotation": "dove",
        "tags": "bird, fly, peace",
        "openmoji_tags": "fly",
        "openmoji_author": "Selina Bauder",
        "openmoji_date": "2018-04-18",
        "skintone": "",
        "skintone_combination": "",
        "skintone_base_emoji": "",
        "skintone_base_hexcode": "",
        "unicode": 0.7,
        "order": 2732
      },
      "top": 576,
      "left": 144,
      "index": 66
    },
    {
      "emoji": {
        "emoji": "🦅",
        "hexcode": "1F985",
        "group": "animals-nature",
        "subgroups": "animal-bird",
        "annotation": "eagle",
        "tags": "bird",
        "openmoji_tags": "fly",
        "openmoji_author": "Selina Bauder",
        "openmoji_date": "2018-04-18",
        "skintone": "",
        "skintone_combination": "",
        "skintone_base_emoji": "",
        "skintone_base_hexcode": "",
        "unicode": 3,
        "order": 2733
      },
      "top": 576,
      "left": 216,
      "index": 67
    },
    {
      "emoji": {
        "emoji": "🦆",
        "hexcode": "1F986",
        "group": "animals-nature",
        "subgroups": "animal-bird",
        "annotation": "duck",
        "tags": "bird",
        "openmoji_tags": "water, fly",
        "openmoji_author": "Selina Bauder",
        "openmoji_date": "2018-04-18",
        "skintone": "",
        "skintone_combination": "",
        "skintone_base_emoji": "",
        "skintone_base_hexcode": "",
        "unicode": 3,
        "order": 2734
      },
      "top": 576,
      "left": 288,
      "index": 68
    },
    {
      "emoji": {
        "emoji": "🦢",
        "hexcode": "1F9A2",
        "group": "animals-nature",
        "subgroups": "animal-bird",
        "annotation": "swan",
        "tags": "bird, cygnet, ugly duckling",
        "openmoji_tags": "",
        "openmoji_author": "Laura Schießer",
        "openmoji_date": "2019-05-06",
        "skintone": "",
        "skintone_combination": "",
        "skintone_base_emoji": "",
        "skintone_base_hexcode": "",
        "unicode": 11,
        "order": 2735
      },
      "top": 576,
      "left": 360,
      "index": 69
    },
    {
      "emoji": {
        "emoji": "🦉",
        "hexcode": "1F989",
        "group": "animals-nature",
        "subgroups": "animal-bird",
        "annotation": "owl",
        "tags": "bird, wise",
        "openmoji_tags": "",
        "openmoji_author": "Selina Bauder",
        "openmoji_date": "2018-04-18",
        "skintone": "",
        "skintone_combination": "",
        "skintone_base_emoji": "",
        "skintone_base_hexcode": "",
        "unicode": 3,
        "order": 2736
      },
      "top": 576,
      "left": 432,
      "index": 70
    },
    {
      "emoji": {
        "emoji": "🦩",
        "hexcode": "1F9A9",
        "group": "animals-nature",
        "subgroups": "animal-bird",
        "annotation": "flamingo",
        "tags": "flamboyant, tropical",
        "openmoji_tags": "flamingo",
        "openmoji_author": "Mariella Steeb",
        "openmoji_date": "2018-04-18",
        "skintone": "",
        "skintone_combination": "",
        "skintone_base_emoji": "",
        "skintone_base_hexcode": "",
        "unicode": 12,
        "order": 2739
      },
      "top": 576,
      "left": 504,
      "index": 71
    },
    {
      "emoji": {
        "emoji": "🦚",
        "hexcode": "1F99A",
        "group": "animals-nature",
        "subgroups": "animal-bird",
        "annotation": "peacock",
        "tags": "bird, ostentatious, peahen, proud",
        "openmoji_tags": "",
        "openmoji_author": "Laura Schießer",
        "openmoji_date": "2019-05-06",
        "skintone": "",
        "skintone_combination": "",
        "skintone_base_emoji": "",
        "skintone_base_hexcode": "",
        "unicode": 11,
        "order": 2740
      },
      "top": 648,
      "left": 0,
      "index": 72
    },
    {
      "emoji": {
        "emoji": "🦜",
        "hexcode": "1F99C",
        "group": "animals-nature",
        "subgroups": "animal-bird",
        "annotation": "parrot",
        "tags": "bird, pirate, talk",
        "openmoji_tags": "",
        "openmoji_author": "Ricarda Krejci",
        "openmoji_date": "2019-05-07",
        "skintone": "",
        "skintone_combination": "",
        "skintone_base_emoji": "",
        "skintone_base_hexcode": "",
        "unicode": 11,
        "order": 2741
      },
      "top": 648,
      "left": 72,
      "index": 73
    },
    {
      "emoji": {
        "emoji": "🐸",
        "hexcode": "1F438",
        "group": "animals-nature",
        "subgroups": "animal-amphibian",
        "annotation": "frog",
        "tags": "face",
        "openmoji_tags": "jump, green",
        "openmoji_author": "Selina Bauder",
        "openmoji_date": "2018-04-18",
        "skintone": "",
        "skintone_combination": "",
        "skintone_base_emoji": "",
        "skintone_base_hexcode": "",
        "unicode": 0.6,
        "order": 2742
      },
      "top": 648,
      "left": 144,
      "index": 74
    },
    {
      "emoji": {
        "emoji": "🐊",
        "hexcode": "1F40A",
        "group": "animals-nature",
        "subgroups": "animal-reptile",
        "annotation": "crocodile",
        "tags": "crocodile",
        "openmoji_tags": "dinosaur",
        "openmoji_author": "Selina Bauder",
        "openmoji_date": "2018-04-18",
        "skintone": "",
        "skintone_combination": "",
        "skintone_base_emoji": "",
        "skintone_base_hexcode": "",
        "unicode": 1,
        "order": 2743
      },
      "top": 648,
      "left": 216,
      "index": 75
    },
    {
      "emoji": {
        "emoji": "🐢",
        "hexcode": "1F422",
        "group": "animals-nature",
        "subgroups": "animal-reptile",
        "annotation": "turtle",
        "tags": "terrapin, tortoise",
        "openmoji_tags": "slow, water, sand",
        "openmoji_author": "Selina Bauder",
        "openmoji_date": "2018-04-18",
        "skintone": "",
        "skintone_combination": "",
        "skintone_base_emoji": "",
        "skintone_base_hexcode": "",
        "unicode": 0.6,
        "order": 2744
      },
      "top": 648,
      "left": 288,
      "index": 76
    },
    {
      "emoji": {
        "emoji": "🦎",
        "hexcode": "1F98E",
        "group": "animals-nature",
        "subgroups": "animal-reptile",
        "annotation": "lizard",
        "tags": "reptile",
        "openmoji_tags": "fast, small",
        "openmoji_author": "Selina Bauder",
        "openmoji_date": "2018-04-18",
        "skintone": "",
        "skintone_combination": "",
        "skintone_base_emoji": "",
        "skintone_base_hexcode": "",
        "unicode": 3,
        "order": 2745
      },
      "top": 648,
      "left": 360,
      "index": 77
    },
    {
      "emoji": {
        "emoji": "🐍",
        "hexcode": "1F40D",
        "group": "animals-nature",
        "subgroups": "animal-reptile",
        "annotation": "snake",
        "tags": "bearer, ophiuchus, serpent, zodiac",
        "openmoji_tags": "wriggle, fast,",
        "openmoji_author": "Selina Bauder",
        "openmoji_date": "2018-04-18",
        "skintone": "",
        "skintone_combination": "",
        "skintone_base_emoji": "",
        "skintone_base_hexcode": "",
        "unicode": 0.6,
        "order": 2746
      },
      "top": 648,
      "left": 432,
      "index": 78
    },
    {
      "emoji": {
        "emoji": "🐲",
        "hexcode": "1F432",
        "group": "animals-nature",
        "subgroups": "animal-reptile",
        "annotation": "dragon face",
        "tags": "dragon, face, fairy tale",
        "openmoji_tags": "fire, fly",
        "openmoji_author": "Selina Bauder",
        "openmoji_date": "2018-04-18",
        "skintone": "",
        "skintone_combination": "",
        "skintone_base_emoji": "",
        "skintone_base_hexcode": "",
        "unicode": 0.6,
        "order": 2747
      },
      "top": 648,
      "left": 504,
      "index": 79
    },
    {
      "emoji": {
        "emoji": "🐉",
        "hexcode": "1F409",
        "group": "animals-nature",
        "subgroups": "animal-reptile",
        "annotation": "dragon",
        "tags": "fairy tale",
        "openmoji_tags": "fire, fly",
        "openmoji_author": "Selina Bauder",
        "openmoji_date": "2018-04-18",
        "skintone": "",
        "skintone_combination": "",
        "skintone_base_emoji": "",
        "skintone_base_hexcode": "",
        "unicode": 1,
        "order": 2748
      },
      "top": 720,
      "left": 0,
      "index": 80
    },
    {
      "emoji": {
        "emoji": "🦕",
        "hexcode": "1F995",
        "group": "animals-nature",
        "subgroups": "animal-reptile",
        "annotation": "sauropod",
        "tags": "brachiosaurus, brontosaurus, diplodocus",
        "openmoji_tags": "dinosaur",
        "openmoji_author": "Selina Bauder",
        "openmoji_date": "2018-04-18",
        "skintone": "",
        "skintone_combination": "",
        "skintone_base_emoji": "",
        "skintone_base_hexcode": "",
        "unicode": 5,
        "order": 2749
      },
      "top": 720,
      "left": 72,
      "index": 81
    },
    {
      "emoji": {
        "emoji": "🦖",
        "hexcode": "1F996",
        "group": "animals-nature",
        "subgroups": "animal-reptile",
        "annotation": "T-Rex",
        "tags": "t-rex, tyrannosaurus rex",
        "openmoji_tags": "dinosaur",
        "openmoji_author": "Selina Bauder",
        "openmoji_date": "2018-04-18",
        "skintone": "",
        "skintone_combination": "",
        "skintone_base_emoji": "",
        "skintone_base_hexcode": "",
        "unicode": 5,
        "order": 2750
      },
      "top": 720,
      "left": 144,
      "index": 82
    },
    {
      "emoji": {
        "emoji": "🐳",
        "hexcode": "1F433",
        "group": "animals-nature",
        "subgroups": "animal-marine",
        "annotation": "spouting whale",
        "tags": "face, spouting, whale",
        "openmoji_tags": "cetacean, swim, animal, water",
        "openmoji_author": "Kris Kowal",
        "openmoji_date": "2020-04-04",
        "skintone": "",
        "skintone_combination": "",
        "skintone_base_emoji": "",
        "skintone_base_hexcode": "",
        "unicode": 0.6,
        "order": 2751
      },
      "top": 720,
      "left": 216,
      "index": 83
    },
    {
      "emoji": {
        "emoji": "🐋",
        "hexcode": "1F40B",
        "group": "animals-nature",
        "subgroups": "animal-marine",
        "annotation": "whale",
        "tags": "whale",
        "openmoji_tags": "cetacean, swim, animal, water",
        "openmoji_author": "Kris Kowal",
        "openmoji_date": "2020-04-04",
        "skintone": "",
        "skintone_combination": "",
        "skintone_base_emoji": "",
        "skintone_base_hexcode": "",
        "unicode": 1,
        "order": 2752
      },
      "top": 720,
      "left": 288,
      "index": 84
    },
    {
      "emoji": {
        "emoji": "🐬",
        "hexcode": "1F42C",
        "group": "animals-nature",
        "subgroups": "animal-marine",
        "annotation": "dolphin",
        "tags": "flipper",
        "openmoji_tags": "cetacean, swim, animal, water",
        "openmoji_author": "Kris Kowal",
        "openmoji_date": "2020-04-04",
        "skintone": "",
        "skintone_combination": "",
        "skintone_base_emoji": "",
        "skintone_base_hexcode": "",
        "unicode": 0.6,
        "order": 2753
      },
      "top": 720,
      "left": 360,
      "index": 85
    },
    {
      "emoji": {
        "emoji": "🐟️",
        "hexcode": "1F41F",
        "group": "animals-nature",
        "subgroups": "animal-marine",
        "annotation": "fish",
        "tags": "pisces, zodiac",
        "openmoji_tags": "swim, animal, water",
        "openmoji_author": "Selina Bauder",
        "openmoji_date": "2018-04-18",
        "skintone": "",
        "skintone_combination": "",
        "skintone_base_emoji": "",
        "skintone_base_hexcode": "",
        "unicode": 0.6,
        "order": 2755
      },
      "top": 720,
      "left": 432,
      "index": 86
    },
    {
      "emoji": {
        "emoji": "🐠",
        "hexcode": "1F420",
        "group": "animals-nature",
        "subgroups": "animal-marine",
        "annotation": "tropical fish",
        "tags": "fish, tropical",
        "openmoji_tags": "swim, animal, water",
        "openmoji_author": "Selina Bauder",
        "openmoji_date": "2018-04-18",
        "skintone": "",
        "skintone_combination": "",
        "skintone_base_emoji": "",
        "skintone_base_hexcode": "",
        "unicode": 0.6,
        "order": 2756
      },
      "top": 720,
      "left": 504,
      "index": 87
    },
    {
      "emoji": {
        "emoji": "🐡",
        "hexcode": "1F421",
        "group": "animals-nature",
        "subgroups": "animal-marine",
        "annotation": "blowfish",
        "tags": "fish",
        "openmoji_tags": "swim, animal, water",
        "openmoji_author": "Selina Bauder",
        "openmoji_date": "2018-04-18",
        "skintone": "",
        "skintone_combination": "",
        "skintone_base_emoji": "",
        "skintone_base_hexcode": "",
        "unicode": 0.6,
        "order": 2757
      },
      "top": 792,
      "left": 0,
      "index": 88
    },
    {
      "emoji": {
        "emoji": "🦈",
        "hexcode": "1F988",
        "group": "animals-nature",
        "subgroups": "animal-marine",
        "annotation": "shark",
        "tags": "fish",
        "openmoji_tags": "swim, animal, water",
        "openmoji_author": "Selina Bauder",
        "openmoji_date": "2018-04-18",
        "skintone": "",
        "skintone_combination": "",
        "skintone_base_emoji": "",
        "skintone_base_hexcode": "",
        "unicode": 3,
        "order": 2758
      },
      "top": 792,
      "left": 72,
      "index": 89
    },
    {
      "emoji": {
        "emoji": "🐙",
        "hexcode": "1F419",
        "group": "animals-nature",
        "subgroups": "animal-marine",
        "annotation": "octopus",
        "tags": "octopus",
        "openmoji_tags": "swim, animal, water",
        "openmoji_author": "Selina Bauder",
        "openmoji_date": "2018-04-18",
        "skintone": "",
        "skintone_combination": "",
        "skintone_base_emoji": "",
        "skintone_base_hexcode": "",
        "unicode": 0.6,
        "order": 2759
      },
      "top": 792,
      "left": 144,
      "index": 90
    },
    {
      "emoji": {
        "emoji": "🐚",
        "hexcode": "1F41A",
        "group": "animals-nature",
        "subgroups": "animal-marine",
        "annotation": "spiral shell",
        "tags": "shell, spiral",
        "openmoji_tags": "beach, sand, water",
        "openmoji_author": "Selina Bauder",
        "openmoji_date": "2018-04-18",
        "skintone": "",
        "skintone_combination": "",
        "skintone_base_emoji": "",
        "skintone_base_hexcode": "",
        "unicode": 0.6,
        "order": 2760
      },
      "top": 792,
      "left": 216,
      "index": 91
    },
    {
      "emoji": {
        "emoji": "🐌",
        "hexcode": "1F40C",
        "group": "animals-nature",
        "subgroups": "animal-bug",
        "annotation": "snail",
        "tags": "snail",
        "openmoji_tags": "",
        "openmoji_author": "Selina Bauder",
        "openmoji_date": "2018-04-18",
        "skintone": "",
        "skintone_combination": "",
        "skintone_base_emoji": "",
        "skintone_base_hexcode": "",
        "unicode": 0.6,
        "order": 2761
      },
      "top": 792,
      "left": 288,
      "index": 92
    },
    {
      "emoji": {
        "emoji": "🦋",
        "hexcode": "1F98B",
        "group": "animals-nature",
        "subgroups": "animal-bug",
        "annotation": "butterfly",
        "tags": "insect, pretty",
        "openmoji_tags": "",
        "openmoji_author": "Selina Bauder",
        "openmoji_date": "2018-04-18",
        "skintone": "",
        "skintone_combination": "",
        "skintone_base_emoji": "",
        "skintone_base_hexcode": "",
        "unicode": 3,
        "order": 2762
      },
      "top": 792,
      "left": 360,
      "index": 93
    },
    {
      "emoji": {
        "emoji": "🐛",
        "hexcode": "1F41B",
        "group": "animals-nature",
        "subgroups": "animal-bug",
        "annotation": "bug",
        "tags": "insect",
        "openmoji_tags": "",
        "openmoji_author": "Selina Bauder",
        "openmoji_date": "2018-04-18",
        "skintone": "",
        "skintone_combination": "",
        "skintone_base_emoji": "",
        "skintone_base_hexcode": "",
        "unicode": 0.6,
        "order": 2763
      },
      "top": 792,
      "left": 432,
      "index": 94
    },
    {
      "emoji": {
        "emoji": "🐜",
        "hexcode": "1F41C",
        "group": "animals-nature",
        "subgroups": "animal-bug",
        "annotation": "ant",
        "tags": "insect",
        "openmoji_tags": "",
        "openmoji_author": "Selina Bauder",
        "openmoji_date": "2018-04-18",
        "skintone": "",
        "skintone_combination": "",
        "skintone_base_emoji": "",
        "skintone_base_hexcode": "",
        "unicode": 0.6,
        "order": 2764
      },
      "top": 792,
      "left": 504,
      "index": 95
    },
    {
      "emoji": {
        "emoji": "🐝",
        "hexcode": "1F41D",
        "group": "animals-nature",
        "subgroups": "animal-bug",
        "annotation": "honeybee",
        "tags": "bee, insect",
        "openmoji_tags": "",
        "openmoji_author": "Selina Bauder",
        "openmoji_date": "2018-04-18",
        "skintone": "",
        "skintone_combination": "",
        "skintone_base_emoji": "",
        "skintone_base_hexcode": "",
        "unicode": 0.6,
        "order": 2765
      },
      "top": 864,
      "left": 0,
      "index": 96
    },
    {
      "emoji": {
        "emoji": "🐞",
        "hexcode": "1F41E",
        "group": "animals-nature",
        "subgroups": "animal-bug",
        "annotation": "lady beetle",
        "tags": "beetle, insect, ladybird, ladybug",
        "openmoji_tags": "",
        "openmoji_author": "Selina Bauder",
        "openmoji_date": "2018-04-18",
        "skintone": "",
        "skintone_combination": "",
        "skintone_base_emoji": "",
        "skintone_base_hexcode": "",
        "unicode": 0.6,
        "order": 2767
      },
      "top": 864,
      "left": 72,
      "index": 97
    },
    {
      "emoji": {
        "emoji": "🦗",
        "hexcode": "1F997",
        "group": "animals-nature",
        "subgroups": "animal-bug",
        "annotation": "cricket",
        "tags": "grasshopper",
        "openmoji_tags": "",
        "openmoji_author": "Selina Bauder",
        "openmoji_date": "2018-04-18",
        "skintone": "",
        "skintone_combination": "",
        "skintone_base_emoji": "",
        "skintone_base_hexcode": "",
        "unicode": 5,
        "order": 2768
      },
      "top": 864,
      "left": 144,
      "index": 98
    },
    {
      "emoji": {
        "emoji": "🕷️",
        "hexcode": "1F577",
        "group": "animals-nature",
        "subgroups": "animal-bug",
        "annotation": "spider",
        "tags": "insect",
        "openmoji_tags": "",
        "openmoji_author": "Selina Bauder",
        "openmoji_date": "2018-04-18",
        "skintone": "",
        "skintone_combination": "",
        "skintone_base_emoji": "",
        "skintone_base_hexcode": "",
        "unicode": 0.7,
        "order": 2771
      },
      "top": 864,
      "left": 216,
      "index": 99
    },
    {
      "emoji": {
        "emoji": "🕸️",
        "hexcode": "1F578",
        "group": "animals-nature",
        "subgroups": "animal-bug",
        "annotation": "spider web",
        "tags": "spider, web",
        "openmoji_tags": "",
        "openmoji_author": "Selina Bauder",
        "openmoji_date": "2018-04-18",
        "skintone": "",
        "skintone_combination": "",
        "skintone_base_emoji": "",
        "skintone_base_hexcode": "",
        "unicode": 0.7,
        "order": 2773
      },
      "top": 864,
      "left": 288,
      "index": 100
    },
    {
      "emoji": {
        "emoji": "🦂",
        "hexcode": "1F982",
        "group": "animals-nature",
        "subgroups": "animal-bug",
        "annotation": "scorpion",
        "tags": "scorpio, zodiac",
        "openmoji_tags": "",
        "openmoji_author": "Selina Bauder",
        "openmoji_date": "2018-04-18",
        "skintone": "",
        "skintone_combination": "",
        "skintone_base_emoji": "",
        "skintone_base_hexcode": "",
        "unicode": 1,
        "order": 2774
      },
      "top": 864,
      "left": 360,
      "index": 101
    },
    {
      "emoji": {
        "emoji": "🦟",
        "hexcode": "1F99F",
        "group": "animals-nature",
        "subgroups": "animal-bug",
        "annotation": "mosquito",
        "tags": "disease, fever, malaria, pest, virus",
        "openmoji_tags": "",
        "openmoji_author": "Ricarda Krejci",
        "openmoji_date": "2019-05-07",
        "skintone": "",
        "skintone_combination": "",
        "skintone_base_emoji": "",
        "skintone_base_hexcode": "",
        "unicode": 11,
        "order": 2775
      },
      "top": 864,
      "left": 432,
      "index": 102
    },
    {
      "emoji": {
        "emoji": "🪰",
        "hexcode": "1FAB0",
        "group": "animals-nature",
        "subgroups": "animal-bug",
        "annotation": "fly",
        "tags": "disease, maggot, pest, rotting",
        "openmoji_tags": "",
        "openmoji_author": "Liz Bravo",
        "openmoji_date": "2020-03-07",
        "skintone": "",
        "skintone_combination": "",
        "skintone_base_emoji": "",
        "skintone_base_hexcode": "",
        "unicode": 13,
        "order": 2776
      },
      "top": 864,
      "left": 504,
      "index": 103
    },
    {
      "emoji": {
        "emoji": "🪱",
        "hexcode": "1FAB1",
        "group": "animals-nature",
        "subgroups": "animal-bug",
        "annotation": "worm",
        "tags": "annelid, earthworm, parasite",
        "openmoji_tags": "",
        "openmoji_author": "Liz Bravo",
        "openmoji_date": "2020-03-07",
        "skintone": "",
        "skintone_combination": "",
        "skintone_base_emoji": "",
        "skintone_base_hexcode": "",
        "unicode": 13,
        "order": 2777
      },
      "top": 936,
      "left": 0,
      "index": 104
    },
    {
      "emoji": {
        "emoji": "🦠",
        "hexcode": "1F9A0",
        "group": "animals-nature",
        "subgroups": "animal-bug",
        "annotation": "microbe",
        "tags": "amoeba, bacteria, virus",
        "openmoji_tags": "",
        "openmoji_author": "Ricarda Krejci",
        "openmoji_date": "2019-05-07",
        "skintone": "",
        "skintone_combination": "",
        "skintone_base_emoji": "",
        "skintone_base_hexcode": "",
        "unicode": 11,
        "order": 2778
      },
      "top": 936,
      "left": 72,
      "index": 105
    },
    {
      "emoji": {
        "emoji": "💐",
        "hexcode": "1F490",
        "group": "animals-nature",
        "subgroups": "plant-flower",
        "annotation": "bouquet",
        "tags": "flower",
        "openmoji_tags": "present, flower, tulip, bouquet",
        "openmoji_author": "Hilda Kalyoncu",
        "openmoji_date": "2018-04-18",
        "skintone": "",
        "skintone_combination": "",
        "skintone_base_emoji": "",
        "skintone_base_hexcode": "",
        "unicode": 0.6,
        "order": 2779
      },
      "top": 936,
      "left": 144,
      "index": 106
    },
    {
      "emoji": {
        "emoji": "🌸",
        "hexcode": "1F338",
        "group": "animals-nature",
        "subgroups": "plant-flower",
        "annotation": "cherry blossom",
        "tags": "blossom, cherry, flower",
        "openmoji_tags": "pink,",
        "openmoji_author": "Hilda Kalyoncu",
        "openmoji_date": "2018-04-18",
        "skintone": "",
        "skintone_combination": "",
        "skintone_base_emoji": "",
        "skintone_base_hexcode": "",
        "unicode": 0.6,
        "order": 2780
      },
      "top": 936,
      "left": 216,
      "index": 107
    },
    {
      "emoji": {
        "emoji": "💮",
        "hexcode": "1F4AE",
        "group": "animals-nature",
        "subgroups": "plant-flower",
        "annotation": "white flower",
        "tags": "flower",
        "openmoji_tags": "",
        "openmoji_author": "Ricarda Krejci",
        "openmoji_date": "2019-05-07",
        "skintone": "",
        "skintone_combination": "",
        "skintone_base_emoji": "",
        "skintone_base_hexcode": "",
        "unicode": 0.6,
        "order": 2781
      },
      "top": 936,
      "left": 288,
      "index": 108
    },
    {
      "emoji": {
        "emoji": "🏵️",
        "hexcode": "1F3F5",
        "group": "animals-nature",
        "subgroups": "plant-flower",
        "annotation": "rosette",
        "tags": "plant",
        "openmoji_tags": "",
        "openmoji_author": "Ricarda Krejci",
        "openmoji_date": "2019-05-07",
        "skintone": "",
        "skintone_combination": "",
        "skintone_base_emoji": "",
        "skintone_base_hexcode": "",
        "unicode": 0.7,
        "order": 2783
      },
      "top": 936,
      "left": 360,
      "index": 109
    },
    {
      "emoji": {
        "emoji": "🌹",
        "hexcode": "1F339",
        "group": "animals-nature",
        "subgroups": "plant-flower",
        "annotation": "rose",
        "tags": "flower",
        "openmoji_tags": "rose, red, nature, present, valentines day",
        "openmoji_author": "Hilda Kalyoncu",
        "openmoji_date": "2018-04-18",
        "skintone": "",
        "skintone_combination": "",
        "skintone_base_emoji": "",
        "skintone_base_hexcode": "",
        "unicode": 0.6,
        "order": 2784
      },
      "top": 936,
      "left": 432,
      "index": 110
    },
    {
      "emoji": {
        "emoji": "🥀",
        "hexcode": "1F940",
        "group": "animals-nature",
        "subgroups": "plant-flower",
        "annotation": "wilted flower",
        "tags": "flower, wilted",
        "openmoji_tags": "rose, wilted, flower, red, sad, plant",
        "openmoji_author": "Hilda Kalyoncu",
        "openmoji_date": "2018-04-18",
        "skintone": "",
        "skintone_combination": "",
        "skintone_base_emoji": "",
        "skintone_base_hexcode": "",
        "unicode": 3,
        "order": 2785
      },
      "top": 936,
      "left": 504,
      "index": 111
    },
    {
      "emoji": {
        "emoji": "🌺",
        "hexcode": "1F33A",
        "group": "animals-nature",
        "subgroups": "plant-flower",
        "annotation": "hibiscus",
        "tags": "flower",
        "openmoji_tags": "pink",
        "openmoji_author": "Hilda Kalyoncu",
        "openmoji_date": "2018-04-18",
        "skintone": "",
        "skintone_combination": "",
        "skintone_base_emoji": "",
        "skintone_base_hexcode": "",
        "unicode": 0.6,
        "order": 2786
      },
      "top": 1008,
      "left": 0,
      "index": 112
    },
    {
      "emoji": {
        "emoji": "🌻",
        "hexcode": "1F33B",
        "group": "animals-nature",
        "subgroups": "plant-flower",
        "annotation": "sunflower",
        "tags": "flower, sun",
        "openmoji_tags": "sun, flower, yellow, summer",
        "openmoji_author": "Hilda Kalyoncu",
        "openmoji_date": "2018-04-18",
        "skintone": "",
        "skintone_combination": "",
        "skintone_base_emoji": "",
        "skintone_base_hexcode": "",
        "unicode": 0.6,
        "order": 2787
      },
      "top": 1008,
      "left": 72,
      "index": 113
    },
    {
      "emoji": {
        "emoji": "🌼",
        "hexcode": "1F33C",
        "group": "animals-nature",
        "subgroups": "plant-flower",
        "annotation": "blossom",
        "tags": "flower",
        "openmoji_tags": "yellow, nature",
        "openmoji_author": "Hilda Kalyoncu",
        "openmoji_date": "2018-04-18",
        "skintone": "",
        "skintone_combination": "",
        "skintone_base_emoji": "",
        "skintone_base_hexcode": "",
        "unicode": 0.6,
        "order": 2788
      },
      "top": 1008,
      "left": 144,
      "index": 114
    },
    {
      "emoji": {
        "emoji": "🌷",
        "hexcode": "1F337",
        "group": "animals-nature",
        "subgroups": "plant-flower",
        "annotation": "tulip",
        "tags": "flower",
        "openmoji_tags": "pink, eastern",
        "openmoji_author": "Hilda Kalyoncu",
        "openmoji_date": "2018-04-18",
        "skintone": "",
        "skintone_combination": "",
        "skintone_base_emoji": "",
        "skintone_base_hexcode": "",
        "unicode": 0.6,
        "order": 2789
      },
      "top": 1008,
      "left": 216,
      "index": 115
    },
    {
      "emoji": {
        "emoji": "🌱",
        "hexcode": "1F331",
        "group": "animals-nature",
        "subgroups": "plant-other",
        "annotation": "seedling",
        "tags": "young",
        "openmoji_tags": "farming, growing, green",
        "openmoji_author": "Hilda Kalyoncu",
        "openmoji_date": "2018-04-18",
        "skintone": "",
        "skintone_combination": "",
        "skintone_base_emoji": "",
        "skintone_base_hexcode": "",
        "unicode": 0.6,
        "order": 2790
      },
      "top": 1008,
      "left": 288,
      "index": 116
    },
    {
      "emoji": {
        "emoji": "🌲",
        "hexcode": "1F332",
        "group": "animals-nature",
        "subgroups": "plant-other",
        "annotation": "evergreen tree",
        "tags": "tree",
        "openmoji_tags": "green, tree, fir, plant",
        "openmoji_author": "Hilda Kalyoncu",
        "openmoji_date": "2018-04-18",
        "skintone": "",
        "skintone_combination": "",
        "skintone_base_emoji": "",
        "skintone_base_hexcode": "",
        "unicode": 1,
        "order": 2792
      },
      "top": 1008,
      "left": 360,
      "index": 117
    },
    {
      "emoji": {
        "emoji": "🌳",
        "hexcode": "1F333",
        "group": "animals-nature",
        "subgroups": "plant-other",
        "annotation": "deciduous tree",
        "tags": "deciduous, shedding, tree",
        "openmoji_tags": "green, tree, huge, plant",
        "openmoji_author": "Hilda Kalyoncu",
        "openmoji_date": "2018-04-18",
        "skintone": "",
        "skintone_combination": "",
        "skintone_base_emoji": "",
        "skintone_base_hexcode": "",
        "unicode": 1,
        "order": 2793
      },
      "top": 1008,
      "left": 432,
      "index": 118
    },
    {
      "emoji": {
        "emoji": "🌴",
        "hexcode": "1F334",
        "group": "animals-nature",
        "subgroups": "plant-other",
        "annotation": "palm tree",
        "tags": "palm, tree",
        "openmoji_tags": "sea, vacation, beach, relax, plant",
        "openmoji_author": "Hilda Kalyoncu",
        "openmoji_date": "2018-04-18",
        "skintone": "",
        "skintone_combination": "",
        "skintone_base_emoji": "",
        "skintone_base_hexcode": "",
        "unicode": 0.6,
        "order": 2794
      },
      "top": 1008,
      "left": 504,
      "index": 119
    },
    {
      "emoji": {
        "emoji": "🌵",
        "hexcode": "1F335",
        "group": "animals-nature",
        "subgroups": "plant-other",
        "annotation": "cactus",
        "tags": "plant",
        "openmoji_tags": "desert, sun, warm, hot, texas, plant",
        "openmoji_author": "Hilda Kalyoncu",
        "openmoji_date": "2018-04-18",
        "skintone": "",
        "skintone_combination": "",
        "skintone_base_emoji": "",
        "skintone_base_hexcode": "",
        "unicode": 0.6,
        "order": 2795
      },
      "top": 1080,
      "left": 0,
      "index": 120
    },
    {
      "emoji": {
        "emoji": "🌾",
        "hexcode": "1F33E",
        "group": "animals-nature",
        "subgroups": "plant-other",
        "annotation": "sheaf of rice",
        "tags": "ear, grain, rice",
        "openmoji_tags": "",
        "openmoji_author": "Hend Hourani",
        "openmoji_date": "2018-11-16",
        "skintone": "",
        "skintone_combination": "",
        "skintone_base_emoji": "",
        "skintone_base_hexcode": "",
        "unicode": 0.6,
        "order": 2796
      },
      "top": 1080,
      "left": 72,
      "index": 121
    },
    {
      "emoji": {
        "emoji": "🌿",
        "hexcode": "1F33F",
        "group": "animals-nature",
        "subgroups": "plant-other",
        "annotation": "herb",
        "tags": "leaf",
        "openmoji_tags": "green",
        "openmoji_author": "Hilda Kalyoncu",
        "openmoji_date": "2018-04-18",
        "skintone": "",
        "skintone_combination": "",
        "skintone_base_emoji": "",
        "skintone_base_hexcode": "",
        "unicode": 0.6,
        "order": 2797
      },
      "top": 1080,
      "left": 144,
      "index": 122
    },
    {
      "emoji": {
        "emoji": "☘️",
        "hexcode": "2618",
        "group": "animals-nature",
        "subgroups": "plant-other",
        "annotation": "shamrock",
        "tags": "plant",
        "openmoji_tags": "green, plant",
        "openmoji_author": "Hilda Kalyoncu",
        "openmoji_date": "2018-04-18",
        "skintone": "",
        "skintone_combination": "",
        "skintone_base_emoji": "",
        "skintone_base_hexcode": "",
        "unicode": 1,
        "order": 2799
      },
      "top": 1080,
      "left": 216,
      "index": 123
    },
    {
      "emoji": {
        "emoji": "🍀",
        "hexcode": "1F340",
        "group": "animals-nature",
        "subgroups": "plant-other",
        "annotation": "four leaf clover",
        "tags": "4, clover, four, four-leaf clover, leaf",
        "openmoji_tags": "luck, four, leaf, green, plant",
        "openmoji_author": "Hilda Kalyoncu",
        "openmoji_date": "2018-04-18",
        "skintone": "",
        "skintone_combination": "",
        "skintone_base_emoji": "",
        "skintone_base_hexcode": "",
        "unicode": 0.6,
        "order": 2800
      },
      "top": 1080,
      "left": 288,
      "index": 124
    },
    {
      "emoji": {
        "emoji": "🍁",
        "hexcode": "1F341",
        "group": "animals-nature",
        "subgroups": "plant-other",
        "annotation": "maple leaf",
        "tags": "falling, leaf, maple",
        "openmoji_tags": "autumn, colorful",
        "openmoji_author": "Hilda Kalyoncu",
        "openmoji_date": "2018-04-18",
        "skintone": "",
        "skintone_combination": "",
        "skintone_base_emoji": "",
        "skintone_base_hexcode": "",
        "unicode": 0.6,
        "order": 2801
      },
      "top": 1080,
      "left": 360,
      "index": 125
    }
  ]
}