{
  "name": "smileys-emotion",
  "columns": 10,
  "rows": 16,
  "width": 720,
  "height": 1152,
  "emojiSize": 72,
  "emojis": [
    {
      "emoji": {
        "emoji": "😀",
        "hexcode": "1F600",
        "group": "smileys-emotion",
        "subgroups": "face-smiling",
        "annotation": "grinning face",
        "tags": "face, grin",
        "openmoji_tags": "smile, happy",
        "openmoji_author": "Emily Jäger",
        "openmoji_date": "2018-04-18",
        "skintone": "",
        "skintone_combination": "",
        "skintone_base_emoji": "",
        "skintone_base_hexcode": "",
        "unicode": 1,
        "order": 1
      },
      "top": 0,
      "left": 0,
      "index": 0
    },
    {
      "emoji": {
        "emoji": "😃",
        "hexcode": "1F603",
        "group": "smileys-emotion",
        "subgroups": "face-smiling",
        "annotation": "grinning face with big eyes",
        "tags": "face, mouth, open, smile",
        "openmoji_tags": "eyes, teeth",
        "openmoji_author": "Emily Jäger",
        "openmoji_date": "2018-04-18",
        "skintone": "",
        "skintone_combination": "",
        "skintone_base_emoji": "",
        "skintone_base_hexcode": "",
        "unicode": 0.6,
        "order": 2
      },
      "top": 0,
      "left": 72,
      "index": 1
    },
    {
      "emoji": {
        "emoji": "😄",
        "hexcode": "1F604",
        "group": "smileys-emotion",
        "subgroups": "face-smiling",
        "annotation": "grinning face with smiling eyes",
        "tags": "eye, face, mouth, open, smile",
        "openmoji_tags": "happy, teeth",
        "openmoji_author": "Emily Jäger",
        "openmoji_date": "2018-04-18",
        "skintone": "",
        "skintone_combination": "",
        "skintone_base_emoji": "",
        "skintone_base_hexcode": "",
        "unicode": 0.6,
        "order": 3
      },
      "top": 0,
      "left": 144,
      "index": 2
    },
    {
      "emoji": {
        "emoji": "😁",
        "hexcode": "1F601",
        "group": "smileys-emotion",
        "subgroups": "face-smiling",
        "annotation": "beaming face with smiling eyes",
        "tags": "eye, face, grin, smile",
        "openmoji_tags": "happy, teeth, mouth",
        "openmoji_author": "Emily Jäger",
        "openmoji_date": "2018-04-18",
        "skintone": "",
        "skintone_combination": "",
        "skintone_base_emoji": "",
        "skintone_base_hexcode": "",
        "unicode": 0.6,
        "order": 4
      },
      "top": 0,
      "left": 216,
      "index": 3
    },
    {
      "emoji": {
        "emoji": "😆",
        "hexcode": "1F606",
        "group": "smileys-emotion",
        "subgroups": "face-smiling",
        "annotation": "grinning squinting face",
        "tags": "face, laugh, mouth, satisfied, smile",
        "openmoji_tags": "",
        "openmoji_author": "Emily Jäger",
        "openmoji_date": "2018-04-18",
        "skintone": "",
        "skintone_combination": "",
        "skintone_base_emoji": "",
        "skintone_base_hexcode": "",
        "unicode": 0.6,
        "order": 5
      },
      "top": 0,
      "left": 288,
      "index": 4
    },
    {
      "emoji": {
        "emoji": "😅",
        "hexcode": "1F605",
        "group": "smileys-emotion",
        "subgroups": "face-smiling",
        "annotation": "grinning face with sweat",
        "tags": "cold, face, open, smile, sweat",
        "openmoji_tags": "laugh",
        "openmoji_author": "Emily Jäger",
        "openmoji_date": "2018-04-18",
        "skintone": "",
        "skintone_combination": "",
        "skintone_base_emoji": "",
        "skintone_base_hexcode": "",
        "unicode": 0.6,
        "order": 6
      },
      "top": 0,
      "left": 360,
      "index": 5
    },
    {
      "emoji": {
        "emoji": "🤣",
        "hexcode": "1F923",
        "group": "smileys-emotion",
        "subgroups": "face-smiling",
        "annotation": "rolling on the floor laughing",
        "tags": "face, floor, laugh, rolling",
        "openmoji_tags": "tears",
        "openmoji_author": "Emily Jäger",
        "openmoji_date": "2018-04-18",
        "skintone": "",
        "skintone_combination": "",
        "skintone_base_emoji": "",
        "skintone_base_hexcode": "",
        "unicode": 3,
        "order": 7
      },
      "top": 0,
      "left": 432,
      "index": 6
    },
    {
      "emoji": {
        "emoji": "😂",
        "hexcode": "1F602",
        "group": "smileys-emotion",
        "subgroups": "face-smiling",
        "annotation": "face with tears of joy",
        "tags": "face, joy, laugh, tear",
        "openmoji_tags": "",
        "openmoji_author": "Emily Jäger",
        "openmoji_date": "2018-04-18",
        "skintone": "",
        "skintone_combination": "",
        "skintone_base_emoji": "",
        "skintone_base_hexcode": "",
        "unicode": 0.6,
        "order": 8
      },
      "top": 0,
      "left": 504,
      "index": 7
    },
    {
      "emoji": {
        "emoji": "🙂",
        "hexcode": "1F642",
        "group": "smileys-emotion",
        "subgroups": "face-smiling",
        "annotation": "slightly smiling face",
        "tags": "face, smile",
        "openmoji_tags": "satisfied",
        "openmoji_author": "Emily Jäger",
        "openmoji_date": "2018-04-18",
        "skintone": "",
        "skintone_combination": "",
        "skintone_base_emoji": "",
        "skintone_base_hexcode": "",
        "unicode": 1,
        "order": 9
      },
      "top": 0,
      "left": 576,
      "index": 8
    },
    {
      "emoji": {
        "emoji": "🙃",
        "hexcode": "1F643",
        "group": "smileys-emotion",
        "subgroups": "face-smiling",
        "annotation": "upside-down face",
        "tags": "face, upside-down",
        "openmoji_tags": "turn",
        "openmoji_author": "Emily Jäger",
        "openmoji_date": "2018-04-18",
        "skintone": "",
        "skintone_combination": "",
        "skintone_base_emoji": "",
        "skintone_base_hexcode": "",
        "unicode": 1,
        "order": 10
      },
      "top": 0,
      "left": 648,
      "index": 9
    },
    {
      "emoji": {
        "emoji": "😉",
        "hexcode": "1F609",
        "group": "smileys-emotion",
        "subgroups": "face-smiling",
        "annotation": "winking face",
        "tags": "face, wink",
        "openmoji_tags": "eye",
        "openmoji_author": "Emily Jäger",
        "openmoji_date": "2018-04-18",
        "skintone": "",
        "skintone_combination": "",
        "skintone_base_emoji": "",
        "skintone_base_hexcode": "",
        "unicode": 0.6,
        "order": 11
      },
      "top": 72,
      "left": 0,
      "index": 10
    },
    {
      "emoji": {
        "emoji": "😊",
        "hexcode": "1F60A",
        "group": "smileys-emotion",
        "subgroups": "face-smiling",
        "annotation": "smiling face with smiling eyes",
        "tags": "blush, eye, face, smile",
        "openmoji_tags": "satisfied",
        "openmoji_author": "Emily Jäger",
        "openmoji_date": "2018-04-18",
        "skintone": "",
        "skintone_combination": "",
        "skintone_base_emoji": "",
        "skintone_base_hexcode": "",
        "unicode": 0.6,
        "order": 12
      },
      "top": 72,
      "left": 72,
      "index": 11
    },
    {
      "emoji": {
        "emoji": "😇",
        "hexcode": "1F607",
        "group": "smileys-emotion",
        "subgroups": "face-smiling",
        "annotation": "smiling face with halo",
        "tags": "angel, face, fantasy, halo, innocent",
        "openmoji_tags": "",
        "openmoji_author": "Emily Jäger",
        "openmoji_date": "2018-04-18",
        "skintone": "",
        "skintone_combination": "",
        "skintone_base_emoji": "",
        "skintone_base_hexcode": "",
        "unicode": 1,
        "order": 13
      },
      "top": 72,
      "left": 144,
      "index": 12
    },
    {
      "emoji": {
        "emoji": "🥰",
        "hexcode": "1F970",
        "group": "smileys-emotion",
        "subgroups": "face-affection",
        "annotation": "smiling face with hearts",
        "tags": "adore, crush, hearts, in love",
        "openmoji_tags": "",
        "openmoji_author": "Antonia Wagner",
        "openmoji_date": "2019-05-03",
        "skintone": "",
        "skintone_combination": "",
        "skintone_base_emoji": "",
        "skintone_base_hexcode": "",
        "unicode": 11,
        "order": 14
      },
      "top": 72,
      "left": 216,
      "index": 13
    },
    {
      "emoji": {
        "emoji": "😍",
        "hexcode": "1F60D",
        "group": "smileys-emotion",
        "subgroups": "face-affection",
        "annotation": "smiling face with heart-eyes",
        "tags": "eye, face, love, smile",
        "openmoji_tags": "hearts, happy",
        "openmoji_author": "Emily Jäger",
        "openmoji_date": "2018-04-18",
        "skintone": "",
        "skintone_combination": "",
        "skintone_base_emoji": "",
        "skintone_base_hexcode": "",
        "unicode": 0.6,
        "order": 15
      },
      "top": 72,
      "left": 288,
      "index": 14
    },
    {
      "emoji": {
        "emoji": "🤩",
        "hexcode": "1F929",
        "group": "smileys-emotion",
        "subgroups": "face-affection",
        "annotation": "star-struck",
        "tags": "eyes, face, grinning, star",
        "openmoji_tags": "surprised",
        "openmoji_author": "Emily Jäger",
        "openmoji_date": "2018-04-18",
        "skintone": "",
        "skintone_combination": "",
        "skintone_base_emoji": "",
        "skintone_base_hexcode": "",
        "unicode": 5,
        "order": 16
      },
      "top": 72,
      "left": 360,
      "index": 15
    },
    {
      "emoji": {
        "emoji": "😘",
        "hexcode": "1F618",
        "group": "smileys-emotion",
        "subgroups": "face-affection",
        "annotation": "face blowing a kiss",
        "tags": "face, kiss",
        "openmoji_tags": "love, happy",
        "openmoji_author": "Emily Jäger",
        "openmoji_date": "2018-04-18",
        "skintone": "",
        "skintone_combination": "",
        "skintone_base_emoji": "",
        "skintone_base_hexcode": "",
        "unicode": 0.6,
        "order": 17
      },
      "top": 72,
      "left": 432,
      "index": 16
    },
    {
      "emoji": {
        "emoji": "😗",
        "hexcode": "1F617",
        "group": "smileys-emotion",
        "subgroups": "face-affection",
        "annotation": "kissing face",
        "tags": "face, kiss",
        "openmoji_tags": "",
        "openmoji_author": "Emily Jäger",
        "openmoji_date": "2018-04-18",
        "skintone": "",
        "skintone_combination": "",
        "skintone_base_emoji": "",
        "skintone_base_hexcode": "",
        "unicode": 1,
        "order": 18
      },
      "top": 72,
      "left": 504,
      "index": 17
    },
    {
      "emoji": {
        "emoji": "☺️",
        "hexcode": "263A",
        "group": "smileys-emotion",
        "subgroups": "face-affection",
        "annotation": "smiling face",
        "tags": "face, outlined, relaxed, smile",
        "openmoji_tags": "satisfied",
        "openmoji_author": "Emily Jäger",
        "openmoji_date": "2018-04-18",
        "skintone": "",
        "skintone_combination": "",
        "skintone_base_emoji": "",
        "skintone_base_hexcode": "",
        "unicode": 0.6,
        "order": 20
      },
      "top": 72,
      "left": 576,
      "index": 18
    },
    {
      "emoji": {
        "emoji": "😚",
        "hexcode": "1F61A",
        "group": "smileys-emotion",
        "subgroups": "face-affection",
        "annotation": "kissing face with closed eyes",
        "tags": "closed, eye, face, kiss",
        "openmoji_tags": "love, happy",
        "openmoji_author": "Emily Jäger",
        "openmoji_date": "2018-04-18",
        "skintone": "",
        "skintone_combination": "",
        "skintone_base_emoji": "",
        "skintone_base_hexcode": "",
        "unicode": 0.6,
        "order": 21
      },
      "top": 72,
      "left": 648,
      "index": 19
    },
    {
      "emoji": {
        "emoji": "😙",
        "hexcode": "1F619",
        "group": "smileys-emotion",
        "subgroups": "face-affection",
        "annotation": "kissing face with smiling eyes",
        "tags": "eye, face, kiss, smile",
        "openmoji_tags": "",
        "openmoji_author": "Emily Jäger",
        "openmoji_date": "2018-04-18",
        "skintone": "",
        "skintone_combination": "",
        "skintone_base_emoji": "",
        "skintone_base_hexcode": "",
        "unicode": 1,
        "order": 22
      },
      "top": 144,
      "left": 0,
      "index": 20
    },
    {
      "emoji": {
        "emoji": "🥲",
        "hexcode": "1F972",
        "group": "smileys-emotion",
        "subgroups": "face-affection",
        "annotation": "smiling face with tear",
        "tags": "grateful, proud, relieved, smiling, tear, touched",
        "openmoji_tags": "",
        "openmoji_author": "Liz Bravo",
        "openmoji_date": "2020-03-07",
        "skintone": "",
        "skintone_combination": "",
        "skintone_base_emoji": "",
        "skintone_base_hexcode": "",
        "unicode": 13,
        "order": 23
      },
      "top": 144,
      "left": 72,
      "index": 21
    },
    {
      "emoji": {
        "emoji": "😋",
        "hexcode": "1F60B",
        "group": "smileys-emotion",
        "subgroups": "face-tongue",
        "annotation": "face savoring food",
        "tags": "delicious, face, savouring, smile, yum",
        "openmoji_tags": "yummy, tongue",
        "openmoji_author": "Emily Jäger",
        "openmoji_date": "2018-04-18",
        "skintone": "",
        "skintone_combination": "",
        "skintone_base_emoji": "",
        "skintone_base_hexcode": "",
        "unicode": 0.6,
        "order": 24
      },
      "top": 144,
      "left": 144,
      "index": 22
    },
    {
      "emoji": {
        "emoji": "😛",
        "hexcode": "1F61B",
        "group": "smileys-emotion",
        "subgroups": "face-tongue",
        "annotation": "face with tongue",
        "tags": "face, tongue",
        "openmoji_tags": "",
        "openmoji_author": "Mariella Steeb",
        "openmoji_date": "2018-04-18",
        "skintone": "",
        "skintone_combination": "",
        "skintone_base_emoji": "",
        "skintone_base_hexcode": "",
        "unicode": 1,
        "order": 25
      },
      "top": 144,
      "left": 216,
      "index": 23
    },
    {
      "emoji": {
        "emoji": "😜",
        "hexcode": "1F61C",
        "group": "smileys-emotion",
        "subgroups": "face-tongue",
        "annotation": "winking face with tongue",
        "tags": "eye, face, joke, tongue, wink",
        "openmoji_tags": "",
        "openmoji_author": "Mariella Steeb",
        "openmoji_date": "2018-04-18",
        "skintone": "",
        "skintone_combination": "",
        "skintone_base_emoji": "",
        "skintone_base_hexcode": "",
        "unicode": 0.6,
        "order": 26
      },
      "top": 144,
      "left": 288,
      "index": 24
    },
    {
      "emoji": {
        "emoji": "🤪",
        "hexcode": "1F92A",
        "group": "smileys-emotion",
        "subgroups": "face-tongue",
        "annotation": "zany face",
        "tags": "eye, goofy, large, small",
        "openmoji_tags": "",
        "openmoji_author": "Mariella Steeb",
        "openmoji_date": "2018-04-18",
        "skintone": "",
        "skintone_combination": "",
        "skintone_base_emoji": "",
        "skintone_base_hexcode": "",
        "unicode": 5,
        "order": 27
      },
      "top": 144,
      "left": 360,
      "index": 25
    },
    {
      "emoji": {
        "emoji": "😝",
        "hexcode": "1F61D",
        "group": "smileys-emotion",
        "subgroups": "face-tongue",
        "annotation": "squinting face with tongue",
        "tags": "eye, face, horrible, taste, tongue",
        "openmoji_tags": "",
        "openmoji_author": "Mariella Steeb",
        "openmoji_date": "2018-04-18",
        "skintone": "",
        "skintone_combination": "",
        "skintone_base_emoji": "",
        "skintone_base_hexcode": "",
        "unicode": 0.6,
        "order": 28
      },
      "top": 144,
      "left": 432,
      "index": 26
    },
    {
      "emoji": {
        "emoji": "🤑",
        "hexcode": "1F911",
        "group": "smileys-emotion",
        "subgroups": "face-tongue",
        "annotation": "money-mouth face",
        "tags": "face, money, mouth",
        "openmoji_tags": "tongue, dollar",
        "openmoji_author": "Emily Jäger",
        "openmoji_date": "2018-04-18",
        "skintone": "",
        "skintone_combination": "",
        "skintone_base_emoji": "",
        "skintone_base_hexcode": "",
        "unicode": 1,
        "order": 29
      },
      "top": 144,
      "left": 504,
      "index": 27
    },
    {
      "emoji": {
        "emoji": "🤗",
        "hexcode": "1F917",
        "group": "smileys-emotion",
        "subgroups": "face-hand",
        "annotation": "hugging face",
        "tags": "face, hug, hugging",
        "openmoji_tags": "hands",
        "openmoji_author": "Emily Jäger",
        "openmoji_date": "2018-04-18",
        "skintone": "",
        "skintone_combination": "",
        "skintone_base_emoji": "",
        "skintone_base_hexcode": "",
        "unicode": 1,
        "order": 30
      },
      "top": 144,
      "left": 576,
      "index": 28
    },
    {
      "emoji": {
        "emoji": "🤭",
        "hexcode": "1F92D",
        "group": "smileys-emotion",
        "subgroups": "face-hand",
        "annotation": "face with hand over mouth",
        "tags": "whoops",
        "openmoji_tags": "hand, mouth",
        "openmoji_author": "Emily Jäger",
        "openmoji_date": "2018-04-18",
        "skintone": "",
        "skintone_combination": "",
        "skintone_base_emoji": "",
        "skintone_base_hexcode": "",
        "unicode": 5,
        "order": 31
      },
      "top": 144,
      "left": 648,
      "index": 29
    },
    {
      "emoji": {
        "emoji": "🤫",
        "hexcode": "1F92B",
        "group": "smileys-emotion",
        "subgroups": "face-hand",
        "annotation": "shushing face",
        "tags": "quiet, shush",
        "openmoji_tags": "hand, silent",
        "openmoji_author": "Emily Jäger",
        "openmoji_date": "2018-04-18",
        "skintone": "",
        "skintone_combination": "",
        "skintone_base_emoji": "",
        "skintone_base_hexcode": "",
        "unicode": 5,
        "order": 32
      },
      "top": 216,
      "left": 0,
      "index": 30
    },
    {
      "emoji": {
        "emoji": "🤔",
        "hexcode": "1F914",
        "group": "smileys-emotion",
        "subgroups": "face-hand",
        "annotation": "thinking face",
        "tags": "face, thinking",
        "openmoji_tags": "hand, overthinking",
        "openmoji_author": "Emily Jäger",
        "openmoji_date": "2018-04-18",
        "skintone": "",
        "skintone_combination": "",
        "skintone_base_emoji": "",
        "skintone_base_hexcode": "",
        "unicode": 1,
        "order": 33
      },
      "top": 216,
      "left": 72,
      "index": 31
    },
    {
      "emoji": {
        "emoji": "🤐",
        "hexcode": "1F910",
        "group": "smileys-emotion",
        "subgroups": "face-neutral-skeptical",
        "annotation": "zipper-mouth face",
        "tags": "face, mouth, zipper",
        "openmoji_tags": "",
        "openmoji_author": "Emily Jäger",
        "openmoji_date": "2018-04-18",
        "skintone": "",
        "skintone_combination": "",
        "skintone_base_emoji": "",
        "skintone_base_hexcode": "",
        "unicode": 1,
        "order": 34
      },
      "top": 216,
      "left": 144,
      "index": 32
    },
    {
      "emoji": {
        "emoji": "🤨",
        "hexcode": "1F928",
        "group": "smileys-emotion",
        "subgroups": "face-neutral-skeptical",
        "annotation": "face with raised eyebrow",
        "tags": "distrust, skeptic",
        "openmoji_tags": "suspiciously",
        "openmoji_author": "Emily Jäger",
        "openmoji_date": "2018-04-18",
        "skintone": "",
        "skintone_combination": "",
        "skintone_base_emoji": "",
        "skintone_base_hexcode": "",
        "unicode": 5,
        "order": 35
      },
      "top": 216,
      "left": 216,
      "index": 33
    },
    {
      "emoji": {
        "emoji": "😐️",
        "hexcode": "1F610",
        "group": "smileys-emotion",
        "subgroups": "face-neutral-skeptical",
        "annotation": "neutral face",
        "tags": "deadpan, face, meh, neutral",
        "openmoji_tags": "",
        "openmoji_author": "Mariella Steeb",
        "openmoji_date": "2018-04-18",
        "skintone": "",
        "skintone_combination": "",
        "skintone_base_emoji": "",
        "skintone_base_hexcode": "",
        "unicode": 0.7,
        "order": 36
      },
      "top": 216,
      "left": 288,
      "index": 34
    },
    {
      "emoji": {
        "emoji": "😑",
        "hexcode": "1F611",
        "group": "smileys-emotion",
        "subgroups": "face-neutral-skeptical",
        "annotation": "expressionless face",
        "tags": "expressionless, face, inexpressive, meh, unexpressive",
        "openmoji_tags": "",
        "openmoji_author": "Mariella Steeb",
        "openmoji_date": "2018-04-18",
        "skintone": "",
        "skintone_combination": "",
        "skintone_base_emoji": "",
        "skintone_base_hexcode": "",
        "unicode": 1,
        "order": 37
      },
      "top": 216,
      "left": 360,
      "index": 35
    },
    {
      "emoji": {
        "emoji": "😶",
        "hexcode": "1F636",
        "group": "smileys-emotion",
        "subgroups": "face-neutral-skeptical",
        "annotation": "face without mouth",
        "tags": "face, mouth, quiet, silent",
        "openmoji_tags": "shhh",
        "openmoji_author": "Emily Jäger",
        "openmoji_date": "2018-04-18",
        "skintone": "",
        "skintone_combination": "",
        "skintone_base_emoji": "",
        "skintone_base_hexcode": "",
        "unicode": 1,
        "order": 38
      },
      "top": 216,
      "left": 432,
      "index": 36
    },
    {
      "emoji": {
        "emoji": "😏",
        "hexcode": "1F60F",
        "group": "smileys-emotion",
        "subgroups": "face-neutral-skeptical",
        "annotation": "smirking face",
        "tags": "face, smirk",
        "openmoji_tags": "",
        "openmoji_author": "Mariella Steeb",
        "openmoji_date": "2018-04-18",
        "skintone": "",
        "skintone_combination": "",
        "skintone_base_emoji": "",
        "skintone_base_hexcode": "",
        "unicode": 0.6,
        "order": 39
      },
      "top": 216,
      "left": 504,
      "index": 37
    },
    {
      "emoji": {
        "emoji": "😒",
        "hexcode": "1F612",
        "group": "smileys-emotion",
        "subgroups": "face-neutral-skeptical",
        "annotation": "unamused face",
        "tags": "face, unamused, unhappy",
        "openmoji_tags": "",
        "openmoji_author": "Mariella Steeb",
        "openmoji_date": "2018-04-18",
        "skintone": "",
        "skintone_combination": "",
        "skintone_base_emoji": "",
        "skintone_base_hexcode": "",
        "unicode": 0.6,
        "order": 40
      },
      "top": 216,
      "left": 576,
      "index": 38
    },
    {
      "emoji": {
        "emoji": "🙄",
        "hexcode": "1F644",
        "group": "smileys-emotion",
        "subgroups": "face-neutral-skeptical",
        "annotation": "face with rolling eyes",
        "tags": "eyeroll, eyes, face, rolling",
        "openmoji_tags": "annoyed",
        "openmoji_author": "Emily Jäger",
        "openmoji_date": "2018-04-18",
        "skintone": "",
        "skintone_combination": "",
        "skintone_base_emoji": "",
        "skintone_base_hexcode": "",
        "unicode": 1,
        "order": 41
      },
      "top": 216,
      "left": 648,
      "index": 39
    },
    {
      "emoji": {
        "emoji": "😬",
        "hexcode": "1F62C",
        "group": "smileys-emotion",
        "subgroups": "face-neutral-skeptical",
        "annotation": "grimacing face",
        "tags": "face, grimace",
        "openmoji_tags": "awkward",
        "openmoji_author": "Daniel Utz",
        "openmoji_date": "2019-11-11",
        "skintone": "",
        "skintone_combination": "",
        "skintone_base_emoji": "",
        "skintone_base_hexcode": "",
        "unicode": 1,
        "order": 42
      },
      "top": 288,
      "left": 0,
      "index": 40
    },
    {
      "emoji": {
        "emoji": "🤥",
        "hexcode": "1F925",
        "group": "smileys-emotion",
        "subgroups": "face-neutral-skeptical",
        "annotation": "lying face",
        "tags": "face, lie, pinocchio",
        "openmoji_tags": "nose, long",
        "openmoji_author": "Emily Jäger",
        "openmoji_date": "2018-04-18",
        "skintone": "",
        "skintone_combination": "",
        "skintone_base_emoji": "",
        "skintone_base_hexcode": "",
        "unicode": 3,
        "order": 43
      },
      "top": 288,
      "left": 72,
      "index": 41
    },
    {
      "emoji": {
        "emoji": "😌",
        "hexcode": "1F60C",
        "group": "smileys-emotion",
        "subgroups": "face-sleepy",
        "annotation": "relieved face",
        "tags": "face, relieved",
        "openmoji_tags": "",
        "openmoji_author": "Mariella Steeb",
        "openmoji_date": "2018-04-18",
        "skintone": "",
        "skintone_combination": "",
        "skintone_base_emoji": "",
        "skintone_base_hexcode": "",
        "unicode": 0.6,
        "order": 44
      },
      "top": 288,
      "left": 144,
      "index": 42
    },
    {
      "emoji": {
        "emoji": "😔",
        "hexcode": "1F614",
        "group": "smileys-emotion",
        "subgroups": "face-sleepy",
        "annotation": "pensive face",
        "tags": "dejected, face, pensive",
        "openmoji_tags": "",
        "openmoji_author": "Mariella Steeb",
        "openmoji_date": "2018-04-18",
        "skintone": "",
        "skintone_combination": "",
        "skintone_base_emoji": "",
        "skintone_base_hexcode": "",
        "unicode": 0.6,
        "order": 45
      },
      "top": 288,
      "left": 216,
      "index": 43
    },
    {
      "emoji": {
        "emoji": "😪",
        "hexcode": "1F62A",
        "group": "smileys-emotion",
        "subgroups": "face-sleepy",
        "annotation": "sleepy face",
        "tags": "face, sleep",
        "openmoji_tags": "snot bubble, side-tear",
        "openmoji_author": "Mariella Steeb",
        "openmoji_date": "2018-04-18",
        "skintone": "",
        "skintone_combination": "",
        "skintone_base_emoji": "",
        "skintone_base_hexcode": "",
        "unicode": 0.6,
        "order": 46
      },
      "top": 288,
      "left": 288,
      "index": 44
    },
    {
      "emoji": {
        "emoji": "🤤",
        "hexcode": "1F924",
        "group": "smileys-emotion",
        "subgroups": "face-sleepy",
        "annotation": "drooling face",
        "tags": "drooling, face",
        "openmoji_tags": "hungry, yummy",
        "openmoji_author": "Emily Jäger",
        "openmoji_date": "2018-04-18",
        "skintone": "",
        "skintone_combination": "",
        "skintone_base_emoji": "",
        "skintone_base_hexcode": "",
        "unicode": 3,
        "order": 47
      },
      "top": 288,
      "left": 360,
      "index": 45
    },
    {
      "emoji": {
        "emoji": "😴",
        "hexcode": "1F634",
        "group": "smileys-emotion",
        "subgroups": "face-sleepy",
        "annotation": "sleeping face",
        "tags": "face, sleep, zzz",
        "openmoji_tags": "tired",
        "openmoji_author": "Emily Jäger",
        "openmoji_date": "2018-04-18",
        "skintone": "",
        "skintone_combination": "",
        "skintone_base_emoji": "",
        "skintone_base_hexcode": "",
        "unicode": 1,
        "order": 48
      },
      "top": 288,
      "left": 432,
      "index": 46
    },
    {
      "emoji": {
        "emoji": "😷",
        "hexcode": "1F637",
        "group": "smileys-emotion",
        "subgroups": "face-unwell",
        "annotation": "face with medical mask",
        "tags": "cold, doctor, face, mask, sick",
        "openmoji_tags": "ill",
        "openmoji_author": "Emily Jäger",
        "openmoji_date": "2018-04-18",
        "skintone": "",
        "skintone_combination": "",
        "skintone_base_emoji": "",
        "skintone_base_hexcode": "",
        "unicode": 0.6,
        "order": 49
      },
      "top": 288,
      "left": 504,
      "index": 47
    },
    {
      "emoji": {
        "emoji": "🤒",
        "hexcode": "1F912",
        "group": "smileys-emotion",
        "subgroups": "face-unwell",
        "annotation": "face with thermometer",
        "tags": "face, ill, sick, thermometer",
        "openmoji_tags": "fever",
        "openmoji_author": "Emily Jäger",
        "openmoji_date": "2018-04-18",
        "skintone": "",
        "skintone_combination": "",
        "skintone_base_emoji": "",
        "skintone_base_hexcode": "",
        "unicode": 1,
        "order": 50
      },
      "top": 288,
      "left": 576,
      "index": 48
    },
    {
      "emoji": {
        "emoji": "🤕",
        "hexcode": "1F915",
        "group": "smileys-emotion",
        "subgroups": "face-unwell",
        "annotation": "face with head-bandage",
        "tags": "bandage, face, hurt, injury",
        "openmoji_tags": "head",
        "openmoji_author": "Emily Jäger",
        "openmoji_date": "2018-04-18",
        "skintone": "",
        "skintone_combination": "",
        "skintone_base_emoji": "",
        "skintone_base_hexcode": "",
        "unicode": 1,
        "order": 51
      },
      "top": 288,
      "left": 648,
      "index": 49
    },
    {
      "emoji": {
        "emoji": "🤢",
        "hexcode": "1F922",
        "group": "smileys-emotion",
        "subgroups": "face-unwell",
        "annotation": "nauseated face",
        "tags": "face, nauseated, vomit",
        "openmoji_tags": "green",
        "openmoji_author": "Emily Jäger",
        "openmoji_date": "2018-04-18",
        "skintone": "",
        "skintone_combination": "",
        "skintone_base_emoji": "",
        "skintone_base_hexcode": "",
        "unicode": 3,
        "order": 52
      },
      "top": 360,
      "left": 0,
      "index": 50
    },
    {
      "emoji": {
        "emoji": "🤮",
        "hexcode": "1F92E",
        "group": "smileys-emotion",
        "subgroups": "face-unwell",
        "annotation": "face vomiting",
        "tags": "sick, vomit",
        "openmoji_tags": "",
        "openmoji_author": "Emily Jäger",
        "openmoji_date": "2018-04-18",
        "skintone": "",
        "skintone_combination": "",
        "skintone_base_emoji": "",
        "skintone_base_hexcode": "",
        "unicode": 5,
        "order": 53
      },
      "top": 360,
      "left": 72,
      "index": 51
    },
    {
      "emoji": {
        "emoji": "🤧",
        "hexcode": "1F927",
        "group": "smileys-emotion",
        "subgroups": "face-unwell",
        "annotation": "sneezing face",
        "tags": "face, gesundheit, sneeze",
        "openmoji_tags": "tissue",
        "openmoji_author": "Emily Jäger",
        "openmoji_date": "2018-04-18",
        "skintone": "",
        "skintone_combination": "",
        "skintone_base_emoji": "",
        "skintone_base_hexcode": "",
        "unicode": 3,
        "order": 54
      },
      "top": 360,
      "left": 144,
      "index": 52
    },
    {
      "emoji": {
        "emoji": "🥵",
        "hexcode": "1F975",
        "group": "smileys-emotion",
        "subgroups": "face-unwell",
        "annotation": "hot face",
        "tags": "feverish, heat stroke, hot, red-faced, sweating",
        "openmoji_tags": "",
        "openmoji_author": "Antonia Wagner",
        "openmoji_date": "2019-05-03",
        "skintone": "",
        "skintone_combination": "",
        "skintone_base_emoji": "",
        "skintone_base_hexcode": "",
        "unicode": 11,
        "order": 55
      },
      "top": 360,
      "left": 216,
      "index": 53
    },
    {
      "emoji": {
        "emoji": "🥶",
        "hexcode": "1F976",
        "group": "smileys-emotion",
        "subgroups": "face-unwell",
        "annotation": "cold face",
        "tags": "blue-faced, cold, freezing, frostbite, icicles",
        "openmoji_tags": "",
        "openmoji_author": "Antonia Wagner",
        "openmoji_date": "2019-05-03",
        "skintone": "",
        "skintone_combination": "",
        "skintone_base_emoji": "",
        "skintone_base_hexcode": "",
        "unicode": 11,
        "order": 56
      },
      "top": 360,
      "left": 288,
      "index": 54
    },
    {
      "emoji": {
        "emoji": "🥴",
        "hexcode": "1F974",
        "group": "smileys-emotion",
        "subgroups": "face-unwell",
        "annotation": "woozy face",
        "tags": "dizzy, intoxicated, tipsy, uneven eyes, wavy mouth",
        "openmoji_tags": "",
        "openmoji_author": "Antonia Wagner",
        "openmoji_date": "2019-05-03",
        "skintone": "",
        "skintone_combination": "",
        "skintone_base_emoji": "",
        "skintone_base_hexcode": "",
        "unicode": 11,
        "order": 57
      },
      "top": 360,
      "left": 360,
      "index": 55
    },
    {
      "emoji": {
        "emoji": "😵",
        "hexcode": "1F635",
        "group": "smileys-emotion",
        "subgroups": "face-unwell",
        "annotation": "dizzy face",
        "tags": "dizzy, face",
        "openmoji_tags": "dead eyes",
        "openmoji_author": "Mariella Steeb",
        "openmoji_date": "2018-04-18",
        "skintone": "",
        "skintone_combination": "",
        "skintone_base_emoji": "",
        "skintone_base_hexcode": "",
        "unicode": 0.6,
        "order": 58
      },
      "top": 360,
      "left": 432,
      "index": 56
    },
    {
      "emoji": {
        "emoji": "🤯",
        "hexcode": "1F92F",
        "group": "smileys-emotion",
        "subgroups": "face-unwell",
        "annotation": "exploding head",
        "tags": "mind blown, shocked",
        "openmoji_tags": "explosion",
        "openmoji_author": "Tara Lynn Connelly",
        "openmoji_date": "2020-04-13",
        "skintone": "",
        "skintone_combination": "",
        "skintone_base_emoji": "",
        "skintone_base_hexcode": "",
        "unicode": 5,
        "order": 59
      },
      "top": 360,
      "left": 504,
      "index": 57
    },
    {
      "emoji": {
        "emoji": "🤠",
        "hexcode": "1F920",
        "group": "smileys-emotion",
        "subgroups": "face-hat",
        "annotation": "cowboy hat face",
        "tags": "cowboy, cowgirl, face, hat",
        "openmoji_tags": "howdy",
        "openmoji_author": "Emily Jäger",
        "openmoji_date": "2018-04-18",
        "skintone": "",
        "skintone_combination": "",
        "skintone_base_emoji": "",
        "skintone_base_hexcode": "",
        "unicode": 3,
        "order": 60
      },
      "top": 360,
      "left": 576,
      "index": 58
    },
    {
      "emoji": {
        "emoji": "🥳",
        "hexcode": "1F973",
        "group": "smileys-emotion",
        "subgroups": "face-hat",
        "annotation": "partying face",
        "tags": "celebration, hat, horn, party",
        "openmoji_tags": "",
        "openmoji_author": "Antonia Wagner",
        "openmoji_date": "2019-05-03",
        "skintone": "",
        "skintone_combination": "",
        "skintone_base_emoji": "",
        "skintone_base_hexcode": "",
        "unicode": 11,
        "order": 61
      },
      "top": 360,
      "left": 648,
      "index": 59
    },
    {
      "emoji": {
        "emoji": "🥸",
        "hexcode": "1F978",
        "group": "smileys-emotion",
        "subgroups": "face-hat",
        "annotation": "disguised face",
        "tags": "disguise, face, glasses, incognito, nose",
        "openmoji_tags": "",
        "openmoji_author": "Liz Bravo",
        "openmoji_date": "2020-03-07",
        "skintone": "",
        "skintone_combination": "",
        "skintone_base_emoji": "",
        "skintone_base_hexcode": "",
        "unicode": 13,
        "order": 62
      },
      "top": 432,
      "left": 0,
      "index": 60
    },
    {
      "emoji": {
        "emoji": "😎",
        "hexcode": "1F60E",
        "group": "smileys-emotion",
        "subgroups": "face-glasses",
        "annotation": "smiling face with sunglasses",
        "tags": "bright, cool, face, sun, sunglasses",
        "openmoji_tags": "",
        "openmoji_author": "Emily Jäger",
        "openmoji_date": "2018-04-18",
        "skintone": "",
        "skintone_combination": "",
        "skintone_base_emoji": "",
        "skintone_base_hexcode": "",
        "unicode": 1,
        "order": 63
      },
      "top": 432,
      "left": 72,
      "index": 61
    },
    {
      "emoji": {
        "emoji": "🤓",
        "hexcode": "1F913",
        "group": "smileys-emotion",
        "subgroups": "face-glasses",
        "annotation": "nerd face",
        "tags": "face, geek, nerd",
        "openmoji_tags": "glasses, learning",
        "openmoji_author": "Emily Jäger",
        "openmoji_date": "2018-04-18",
        "skintone": "",
        "skintone_combination": "",
        "skintone_base_emoji": "",
        "skintone_base_hexcode": "",
        "unicode": 1,
        "order": 64
      },
      "top": 432,
      "left": 144,
      "index": 62
    },
    {
      "emoji": {
        "emoji": "🧐",
        "hexcode": "1F9D0",
        "group": "smileys-emotion",
        "subgroups": "face-glasses",
        "annotation": "face with monocle",
        "tags": "stuffy",
        "openmoji_tags": "glasses, intelligent",
        "openmoji_author": "Emily Jäger",
        "openmoji_date": "2018-04-18",
        "skintone": "",
        "skintone_combination": "",
        "skintone_base_emoji": "",
        "skintone_base_hexcode": "",
        "unicode": 5,
        "order": 65
      },
      "top": 432,
      "left": 216,
      "index": 63
    },
    {
      "emoji": {
        "emoji": "😕",
        "hexcode": "1F615",
        "group": "smileys-emotion",
        "subgroups": "face-concerned",
        "annotation": "confused face",
        "tags": "confused, face, meh",
        "openmoji_tags": "",
        "openmoji_author": "Mariella Steeb",
        "openmoji_date": "2018-04-18",
        "skintone": "",
        "skintone_combination": "",
        "skintone_base_emoji": "",
        "skintone_base_hexcode": "",
        "unicode": 1,
        "order": 66
      },
      "top": 432,
      "left": 288,
      "index": 64
    },
    {
      "emoji": {
        "emoji": "😟",
        "hexcode": "1F61F",
        "group": "smileys-emotion",
        "subgroups": "face-concerned",
        "annotation": "worried face",
        "tags": "face, worried",
        "openmoji_tags": "",
        "openmoji_author": "Mariella Steeb",
        "openmoji_date": "2018-04-18",
        "skintone": "",
        "skintone_combination": "",
        "skintone_base_emoji": "",
        "skintone_base_hexcode": "",
        "unicode": 1,
        "order": 67
      },
      "top": 432,
      "left": 360,
      "index": 65
    },
    {
      "emoji": {
        "emoji": "🙁",
        "hexcode": "1F641",
        "group": "smileys-emotion",
        "subgroups": "face-concerned",
        "annotation": "slightly frowning face",
        "tags": "face, frown",
        "openmoji_tags": "",
        "openmoji_author": "Mariella Steeb",
        "openmoji_date": "2018-04-18",
        "skintone": "",
        "skintone_combination": "",
        "skintone_base_emoji": "",
        "skintone_base_hexcode": "",
        "unicode": 1,
        "order": 68
      },
      "top": 432,
      "left": 432,
      "index": 66
    },
    {
      "emoji": {
        "emoji": "☹️",
        "hexcode": "2639",
        "group": "smileys-emotion",
        "subgroups": "face-concerned",
        "annotation": "frowning face",
        "tags": "face, frown",
        "openmoji_tags": "negative",
        "openmoji_author": "Mariella Steeb",
        "openmoji_date": "2018-04-18",
        "skintone": "",
        "skintone_combination": "",
        "skintone_base_emoji": "",
        "skintone_base_hexcode": "",
        "unicode": 0.7,
        "order": 70
      },
      "top": 432,
      "left": 504,
      "index": 67
    },
    {
      "emoji": {
        "emoji": "😮",
        "hexcode": "1F62E",
        "group": "smileys-emotion",
        "subgroups": "face-concerned",
        "annotation": "face with open mouth",
        "tags": "face, mouth, open, sympathy",
        "openmoji_tags": "",
        "openmoji_author": "Mariella Steeb",
        "openmoji_date": "2018-04-18",
        "skintone": "",
        "skintone_combination": "",
        "skintone_base_emoji": "",
        "skintone_base_hexcode": "",
        "unicode": 1,
        "order": 71
      },
      "top": 432,
      "left": 576,
      "index": 68
    },
    {
      "emoji": {
        "emoji": "😯",
        "hexcode": "1F62F",
        "group": "smileys-emotion",
        "subgroups": "face-concerned",
        "annotation": "hushed face",
        "tags": "face, hushed, stunned, surprised",
        "openmoji_tags": "",
        "openmoji_author": "Mariella Steeb",
        "openmoji_date": "2018-04-18",
        "skintone": "",
        "skintone_combination": "",
        "skintone_base_emoji": "",
        "skintone_base_hexcode": "",
        "unicode": 1,
        "order": 72
      },
      "top": 432,
      "left": 648,
      "index": 69
    },
    {
      "emoji": {
        "emoji": "😲",
        "hexcode": "1F632",
        "group": "smileys-emotion",
        "subgroups": "face-concerned",
        "annotation": "astonished face",
        "tags": "astonished, face, shocked, totally",
        "openmoji_tags": "",
        "openmoji_author": "Emily Jäger",
        "openmoji_date": "2018-04-18",
        "skintone": "",
        "skintone_combination": "",
        "skintone_base_emoji": "",
        "skintone_base_hexcode": "",
        "unicode": 0.6,
        "order": 73
      },
      "top": 504,
      "left": 0,
      "index": 70
    },
    {
      "emoji": {
        "emoji": "😳",
        "hexcode": "1F633",
        "group": "smileys-emotion",
        "subgroups": "face-concerned",
        "annotation": "flushed face",
        "tags": "dazed, face, flushed",
        "openmoji_tags": "red jaws",
        "openmoji_author": "Mariella Steeb",
        "openmoji_date": "2018-04-18",
        "skintone": "",
        "skintone_combination": "",
        "skintone_base_emoji": "",
        "skintone_base_hexcode": "",
        "unicode": 0.6,
        "order": 74
      },
      "top": 504,
      "left": 72,
      "index": 71
    },
    {
      "emoji": {
        "emoji": "🥺",
        "hexcode": "1F97A",
        "group": "smileys-emotion",
        "subgroups": "face-concerned",
        "annotation": "pleading face",
        "tags": "begging, mercy, puppy eyes",
        "openmoji_tags": "",
        "openmoji_author": "Antonia Wagner",
        "openmoji_date": "2019-05-03",
        "skintone": "",
        "skintone_combination": "",
        "skintone_base_emoji": "",
        "skintone_base_hexcode": "",
        "unicode": 11,
        "order": 75
      },
      "top": 504,
      "left": 144,
      "index": 72
    },
    {
      "emoji": {
        "emoji": "😦",
        "hexcode": "1F626",
        "group": "smileys-emotion",
        "subgroups": "face-concerned",
        "annotation": "frowning face with open mouth",
        "tags": "face, frown, mouth, open",
        "openmoji_tags": "",
        "openmoji_author": "Mariella Steeb",
        "openmoji_date": "2018-04-18",
        "skintone": "",
        "skintone_combination": "",
        "skintone_base_emoji": "",
        "skintone_base_hexcode": "",
        "unicode": 1,
        "order": 76
      },
      "top": 504,
      "left": 216,
      "index": 73
    },
    {
      "emoji": {
        "emoji": "😧",
        "hexcode": "1F627",
        "group": "smileys-emotion",
        "subgroups": "face-concerned",
        "annotation": "anguished face",
        "tags": "anguished, face",
        "openmoji_tags": "",
        "openmoji_author": "Mariella Steeb",
        "openmoji_date": "2018-04-18",
        "skintone": "",
        "skintone_combination": "",
        "skintone_base_emoji": "",
        "skintone_base_hexcode": "",
        "unicode": 1,
        "order": 77
      },
      "top": 504,
      "left": 288,
      "index": 74
    },
    {
      "emoji": {
        "emoji": "😨",
        "hexcode": "1F628",
        "group": "smileys-emotion",
        "subgroups": "face-concerned",
        "annotation": "fearful face",
        "tags": "face, fear, fearful, scared",
        "openmoji_tags": "",
        "openmoji_author": "Mariella Steeb",
        "openmoji_date": "2018-04-18",
        "skintone": "",
        "skintone_combination": "",
        "skintone_base_emoji": "",
        "skintone_base_hexcode": "",
        "unicode": 0.6,
        "order": 78
      },
      "top": 504,
      "left": 360,
      "index": 75
    },
    {
      "emoji": {
        "emoji": "😰",
        "hexcode": "1F630",
        "group": "smileys-emotion",
        "subgroups": "face-concerned",
        "annotation": "anxious face with sweat",
        "tags": "blue, cold, face, rushed, sweat",
        "openmoji_tags": "anxious, worried, considerate",
        "openmoji_author": "Mariella Steeb",
        "openmoji_date": "2018-04-18",
        "skintone": "",
        "skintone_combination": "",
        "skintone_base_emoji": "",
        "skintone_base_hexcode": "",
        "unicode": 0.6,
        "order": 79
      },
      "top": 504,
      "left": 432,
      "index": 76
    },
    {
      "emoji": {
        "emoji": "😥",
        "hexcode": "1F625",
        "group": "smileys-emotion",
        "subgroups": "face-concerned",
        "annotation": "sad but relieved face",
        "tags": "disappointed, face, relieved, whew",
        "openmoji_tags": "",
        "openmoji_author": "Mariella Steeb",
        "openmoji_date": "2018-04-18",
        "skintone": "",
        "skintone_combination": "",
        "skintone_base_emoji": "",
        "skintone_base_hexcode": "",
        "unicode": 0.6,
        "order": 80
      },
      "top": 504,
      "left": 504,
      "index": 77
    },
    {
      "emoji": {
        "emoji": "😢",
        "hexcode": "1F622",
        "group": "smileys-emotion",
        "subgroups": "face-concerned",
        "annotation": "crying face",
        "tags": "cry, face, sad, tear",
        "openmoji_tags": "",
        "openmoji_author": "Mariella Steeb",
        "openmoji_date": "2018-04-18",
        "skintone": "",
        "skintone_combination": "",
        "skintone_base_emoji": "",
        "skintone_base_hexcode": "",
        "unicode": 0.6,
        "order": 81
      },
      "top": 504,
      "left": 576,
      "index": 78
    },
    {
      "emoji": {
        "emoji": "😭",
        "hexcode": "1F62D",
        "group": "smileys-emotion",
        "subgroups": "face-concerned",
        "annotation": "loudly crying face",
        "tags": "cry, face, sad, sob, tear",
        "openmoji_tags": "",
        "openmoji_author": "Mariella Steeb",
        "openmoji_date": "2018-04-18",
        "skintone": "",
        "skintone_combination": "",
        "skintone_base_emoji": "",
        "skintone_base_hexcode": "",
        "unicode": 0.6,
        "order": 82
      },
      "top": 504,
      "left": 648,
      "index": 79
    },
    {
      "emoji": {
        "emoji": "😱",
        "hexcode": "1F631",
        "group": "smileys-emotion",
        "subgroups": "face-concerned",
        "annotation": "face screaming in fear",
        "tags": "face, fear, munch, scared, scream",
        "openmoji_tags": "open mouth",
        "openmoji_author": "Mariella Steeb",
        "openmoji_date": "2018-04-18",
        "skintone": "",
        "skintone_combination": "",
        "skintone_base_emoji": "",
        "skintone_base_hexcode": "",
        "unicode": 0.6,
        "order": 83
      },
      "top": 576,
      "left": 0,
      "index": 80
    },
    {
      "emoji": {
        "emoji": "😖",
        "hexcode": "1F616",
        "group": "smileys-emotion",
        "subgroups": "face-concerned",
        "annotation": "confounded face",
        "tags": "confounded, face",
        "openmoji_tags": "",
        "openmoji_author": "Mariella Steeb",
        "openmoji_date": "2018-04-18",
        "skintone": "",
        "skintone_combination": "",
        "skintone_base_emoji": "",
        "skintone_base_hexcode": "",
        "unicode": 0.6,
        "order": 84
      },
      "top": 576,
      "left": 72,
      "index": 81
    },
    {
      "emoji": {
        "emoji": "😣",
        "hexcode": "1F623",
        "group": "smileys-emotion",
        "subgroups": "face-concerned",
        "annotation": "persevering face",
        "tags": "face, persevere",
        "openmoji_tags": "",
        "openmoji_author": "Mariella Steeb",
        "openmoji_date": "2018-04-18",
        "skintone": "",
        "skintone_combination": "",
        "skintone_base_emoji": "",
        "skintone_base_hexcode": "",
        "unicode": 0.6,
        "order": 85
      },
      "top": 576,
      "left": 144,
      "index": 82
    },
    {
      "emoji": {
        "emoji": "😞",
        "hexcode": "1F61E",
        "group": "smileys-emotion",
        "subgroups": "face-concerned",
        "annotation": "disappointed face",
        "tags": "disappointed, face",
        "openmoji_tags": "",
        "openmoji_author": "Mariella Steeb",
        "openmoji_date": "2018-04-18",
        "skintone": "",
        "skintone_combination": "",
        "skintone_base_emoji": "",
        "skintone_base_hexcode": "",
        "unicode": 0.6,
        "order": 86
      },
      "top": 576,
      "left": 216,
      "index": 83
    },
    {
      "emoji": {
        "emoji": "😓",
        "hexcode": "1F613",
        "group": "smileys-emotion",
        "subgroups": "face-concerned",
        "annotation": "downcast face with sweat",
        "tags": "cold, face, sweat",
        "openmoji_tags": "",
        "openmoji_author": "Mariella Steeb",
        "openmoji_date": "2018-04-18",
        "skintone": "",
        "skintone_combination": "",
        "skintone_base_emoji": "",
        "skintone_base_hexcode": "",
        "unicode": 0.6,
        "order": 87
      },
      "top": 576,
      "left": 288,
      "index": 84
    },
    {
      "emoji": {
        "emoji": "😩",
        "hexcode": "1F629",
        "group": "smileys-emotion",
        "subgroups": "face-concerned",
        "annotation": "weary face",
        "tags": "face, tired, weary",
        "openmoji_tags": "distraught",
        "openmoji_author": "Mariella Steeb",
        "openmoji_date": "2018-04-18",
        "skintone": "",
        "skintone_combination": "",
        "skintone_base_emoji": "",
        "skintone_base_hexcode": "",
        "unicode": 0.6,
        "order": 88
      },
      "top": 576,
      "left": 360,
      "index": 85
    },
    {
      "emoji": {
        "emoji": "😫",
        "hexcode": "1F62B",
        "group": "smileys-emotion",
        "subgroups": "face-concerned",
        "annotation": "tired face",
        "tags": "face, tired",
        "openmoji_tags": "exhausted",
        "openmoji_author": "Mariella Steeb",
        "openmoji_date": "2018-04-18",
        "skintone": "",
        "skintone_combination": "",
        "skintone_base_emoji": "",
        "skintone_base_hexcode": "",
        "unicode": 0.6,
        "order": 89
      },
      "top": 576,
      "left": 432,
      "index": 86
    },
    {
      "emoji": {
        "emoji": "🥱",
        "hexcode": "1F971",
        "group": "smileys-emotion",
        "subgroups": "face-concerned",
        "annotation": "yawning face",
        "tags": "bored, tired, yawn",
        "openmoji_tags": "",
        "openmoji_author": "Laura Dworatschek",
        "openmoji_date": "2019-05-06",
        "skintone": "",
        "skintone_combination": "",
        "skintone_base_emoji": "",
        "skintone_base_hexcode": "",
        "unicode": 12,
        "order": 90
      },
      "top": 576,
      "left": 504,
      "index": 87
    },
    {
      "emoji": {
        "emoji": "😤",
        "hexcode": "1F624",
        "group": "smileys-emotion",
        "subgroups": "face-negative",
        "annotation": "face with steam from nose",
        "tags": "face, triumph, won",
        "openmoji_tags": "",
        "openmoji_author": "Mariella Steeb",
        "openmoji_date": "2018-04-18",
        "skintone": "",
        "skintone_combination": "",
        "skintone_base_emoji": "",
        "skintone_base_hexcode": "",
        "unicode": 0.6,
        "order": 91
      },
      "top": 576,
      "left": 576,
      "index": 88
    },
    {
      "emoji": {
        "emoji": "😡",
        "hexcode": "1F621",
        "group": "smileys-emotion",
        "subgroups": "face-negative",
        "annotation": "pouting face",
        "tags": "angry, face, mad, pouting, rage, red",
        "openmoji_tags": "",
        "openmoji_author": "Mariella Steeb",
        "openmoji_date": "2018-04-18",
        "skintone": "",
        "skintone_combination": "",
        "skintone_base_emoji": "",
        "skintone_base_hexcode": "",
        "unicode": 0.6,
        "order": 92
      },
      "top": 576,
      "left": 648,
      "index": 89
    },
    {
      "emoji": {
        "emoji": "😠",
        "hexcode": "1F620",
        "group": "smileys-emotion",
        "subgroups": "face-negative",
        "annotation": "angry face",
        "tags": "angry, face, mad",
        "openmoji_tags": "",
        "openmoji_author": "Mariella Steeb",
        "openmoji_date": "2018-04-18",
        "skintone": "",
        "skintone_combination": "",
        "skintone_base_emoji": "",
        "skintone_base_hexcode": "",
        "unicode": 0.6,
        "order": 93
      },
      "top": 648,
      "left": 0,
      "index": 90
    },
    {
      "emoji": {
        "emoji": "🤬",
        "hexcode": "1F92C",
        "group": "smileys-emotion",
        "subgroups": "face-negative",
        "annotation": "face with symbols on mouth",
        "tags": "swearing",
        "openmoji_tags": "angry",
        "openmoji_author": "Mariella Steeb",
        "openmoji_date": "2018-04-18",
        "skintone": "",
        "skintone_combination": "",
        "skintone_base_emoji": "",
        "skintone_base_hexcode": "",
        "unicode": 5,
        "order": 94
      },
      "top": 648,
      "left": 72,
      "index": 91
    },
    {
      "emoji": {
        "emoji": "😈",
        "hexcode": "1F608",
        "group": "smileys-emotion",
        "subgroups": "face-negative",
        "annotation": "smiling face with horns",
        "tags": "face, fairy tale, fantasy, horns, smile",
        "openmoji_tags": "malicious, sardonic",
        "openmoji_author": "Mariella Steeb",
        "openmoji_date": "2018-04-18",
        "skintone": "",
        "skintone_combination": "",
        "skintone_base_emoji": "",
        "skintone_base_hexcode": "",
        "unicode": 1,
        "order": 95
      },
      "top": 648,
      "left": 144,
      "index": 92
    },
    {
      "emoji": {
        "emoji": "👿",
        "hexcode": "1F47F",
        "group": "smileys-emotion",
        "subgroups": "face-negative",
        "annotation": "angry face with horns",
        "tags": "demon, devil, face, fantasy, imp",
        "openmoji_tags": "mean",
        "openmoji_author": "Mariella Steeb",
        "openmoji_date": "2018-04-18",
        "skintone": "",
        "skintone_combination": "",
        "skintone_base_emoji": "",
        "skintone_base_hexcode": "",
        "unicode": 0.6,
        "order": 96
      },
      "top": 648,
      "left": 216,
      "index": 93
    },
    {
      "emoji": {
        "emoji": "💀",
        "hexcode": "1F480",
        "group": "smileys-emotion",
        "subgroups": "face-negative",
        "annotation": "skull",
        "tags": "death, face, fairy tale, monster",
        "openmoji_tags": "skull",
        "openmoji_author": "Mariella Steeb",
        "openmoji_date": "2018-04-18",
        "skintone": "",
        "skintone_combination": "",
        "skintone_base_emoji": "",
        "skintone_base_hexcode": "",
        "unicode": 0.6,
        "order": 97
      },
      "top": 648,
      "left": 288,
      "index": 94
    },
    {
      "emoji": {
        "emoji": "☠️",
        "hexcode": "2620",
        "group": "smileys-emotion",
        "subgroups": "face-negative",
        "annotation": "skull and crossbones",
        "tags": "crossbones, death, face, monster, skull",
        "openmoji_tags": "",
        "openmoji_author": "Mariella Steeb",
        "openmoji_date": "2018-04-18",
        "skintone": "",
        "skintone_combination": "",
        "skintone_base_emoji": "",
        "skintone_base_hexcode": "",
        "unicode": 1,
        "order": 99
      },
      "top": 648,
      "left": 360,
      "index": 95
    },
    {
      "emoji": {
        "emoji": "💩",
        "hexcode": "1F4A9",
        "group": "smileys-emotion",
        "subgroups": "face-costume",
        "annotation": "pile of poo",
        "tags": "dung, face, monster, poo, poop",
        "openmoji_tags": "",
        "openmoji_author": "Mariella Steeb",
        "openmoji_date": "2018-04-18",
        "skintone": "",
        "skintone_combination": "",
        "skintone_base_emoji": "",
        "skintone_base_hexcode": "",
        "unicode": 0.6,
        "order": 100
      },
      "top": 648,
      "left": 432,
      "index": 96
    },
    {
      "emoji": {
        "emoji": "🤡",
        "hexcode": "1F921",
        "group": "smileys-emotion",
        "subgroups": "face-costume",
        "annotation": "clown face",
        "tags": "clown, face",
        "openmoji_tags": "",
        "openmoji_author": "Emily Jäger",
        "openmoji_date": "2018-04-18",
        "skintone": "",
        "skintone_combination": "",
        "skintone_base_emoji": "",
        "skintone_base_hexcode": "",
        "unicode": 3,
        "order": 101
      },
      "top": 648,
      "left": 504,
      "index": 97
    },
    {
      "emoji": {
        "emoji": "👹",
        "hexcode": "1F479",
        "group": "smileys-emotion",
        "subgroups": "face-costume",
        "annotation": "ogre",
        "tags": "creature, face, fairy tale, fantasy, monster",
        "openmoji_tags": "",
        "openmoji_author": "Anne Frauendorf",
        "openmoji_date": "2018-11-16",
        "skintone": "",
        "skintone_combination": "",
        "skintone_base_emoji": "",
        "skintone_base_hexcode": "",
        "unicode": 0.6,
        "order": 102
      },
      "top": 648,
      "left": 576,
      "index": 98
    },
    {
      "emoji": {
        "emoji": "👺",
        "hexcode": "1F47A",
        "group": "smileys-emotion",
        "subgroups": "face-costume",
        "annotation": "goblin",
        "tags": "creature, face, fairy tale, fantasy, monster",
        "openmoji_tags": "",
        "openmoji_author": "Antonia Wagner",
        "openmoji_date": "2019-05-03",
        "skintone": "",
        "skintone_combination": "",
        "skintone_base_emoji": "",
        "skintone_base_hexcode": "",
        "unicode": 0.6,
        "order": 103
      },
      "top": 648,
      "left": 648,
      "index": 99
    },
    {
      "emoji": {
        "emoji": "👻",
        "hexcode": "1F47B",
        "group": "smileys-emotion",
        "subgroups": "face-costume",
        "annotation": "ghost",
        "tags": "creature, face, fairy tale, fantasy, monster",
        "openmoji_tags": "ghost",
        "openmoji_author": "Mariella Steeb",
        "openmoji_date": "2018-04-18",
        "skintone": "",
        "skintone_combination": "",
        "skintone_base_emoji": "",
        "skintone_base_hexcode": "",
        "unicode": 0.6,
        "order": 104
      },
      "top": 720,
      "left": 0,
      "index": 100
    },
    {
      "emoji": {
        "emoji": "👽️",
        "hexcode": "1F47D",
        "group": "smileys-emotion",
        "subgroups": "face-costume",
        "annotation": "alien",
        "tags": "creature, extraterrestrial, face, fantasy, ufo",
        "openmoji_tags": "alien",
        "openmoji_author": "Mariella Steeb",
        "openmoji_date": "2018-04-18",
        "skintone": "",
        "skintone_combination": "",
        "skintone_base_emoji": "",
        "skintone_base_hexcode": "",
        "unicode": 0.6,
        "order": 105
      },
      "top": 720,
      "left": 72,
      "index": 101
    },
    {
      "emoji": {
        "emoji": "👾",
        "hexcode": "1F47E",
        "group": "smileys-emotion",
        "subgroups": "face-costume",
        "annotation": "alien monster",
        "tags": "alien, creature, extraterrestrial, face, monster, ufo",
        "openmoji_tags": "",
        "openmoji_author": "Antonia Wagner",
        "openmoji_date": "2019-05-03",
        "skintone": "",
        "skintone_combination": "",
        "skintone_base_emoji": "",
        "skintone_base_hexcode": "",
        "unicode": 0.6,
        "order": 106
      },
      "top": 720,
      "left": 144,
      "index": 102
    },
    {
      "emoji": {
        "emoji": "🤖",
        "hexcode": "1F916",
        "group": "smileys-emotion",
        "subgroups": "face-costume",
        "annotation": "robot",
        "tags": "face, monster",
        "openmoji_tags": "",
        "openmoji_author": "Mariella Steeb",
        "openmoji_date": "2018-04-18",
        "skintone": "",
        "skintone_combination": "",
        "skintone_base_emoji": "",
        "skintone_base_hexcode": "",
        "unicode": 1,
        "order": 107
      },
      "top": 720,
      "left": 216,
      "index": 103
    },
    {
      "emoji": {
        "emoji": "😺",
        "hexcode": "1F63A",
        "group": "smileys-emotion",
        "subgroups": "cat-face",
        "annotation": "grinning cat",
        "tags": "cat, face, grinning, mouth, open, smile",
        "openmoji_tags": "grinning",
        "openmoji_author": "Emily Jäger",
        "openmoji_date": "2018-04-18",
        "skintone": "",
        "skintone_combination": "",
        "skintone_base_emoji": "",
        "skintone_base_hexcode": "",
        "unicode": 0.6,
        "order": 108
      },
      "top": 720,
      "left": 288,
      "index": 104
    },
    {
      "emoji": {
        "emoji": "😸",
        "hexcode": "1F638",
        "group": "smileys-emotion",
        "subgroups": "cat-face",
        "annotation": "grinning cat with smiling eyes",
        "tags": "cat, eye, face, grin, smile",
        "openmoji_tags": "grinning",
        "openmoji_author": "Emily Jäger",
        "openmoji_date": "2018-04-18",
        "skintone": "",
        "skintone_combination": "",
        "skintone_base_emoji": "",
        "skintone_base_hexcode": "",
        "unicode": 0.6,
        "order": 109
      },
      "top": 720,
      "left": 360,
      "index": 105
    },
    {
      "emoji": {
        "emoji": "😹",
        "hexcode": "1F639",
        "group": "smileys-emotion",
        "subgroups": "cat-face",
        "annotation": "cat with tears of joy",
        "tags": "cat, face, joy, tear",
        "openmoji_tags": "laughing, smile",
        "openmoji_author": "Emily Jäger",
        "openmoji_date": "2018-04-18",
        "skintone": "",
        "skintone_combination": "",
        "skintone_base_emoji": "",
        "skintone_base_hexcode": "",
        "unicode": 0.6,
        "order": 110
      },
      "top": 720,
      "left": 432,
      "index": 106
    },
    {
      "emoji": {
        "emoji": "😻",
        "hexcode": "1F63B",
        "group": "smileys-emotion",
        "subgroups": "cat-face",
        "annotation": "smiling cat with heart-eyes",
        "tags": "cat, eye, face, heart, love, smile",
        "openmoji_tags": "hearts, red",
        "openmoji_author": "Emily Jäger",
        "openmoji_date": "2018-04-18",
        "skintone": "",
        "skintone_combination": "",
        "skintone_base_emoji": "",
        "skintone_base_hexcode": "",
        "unicode": 0.6,
        "order": 111
      },
      "top": 720,
      "left": 504,
      "index": 107
    },
    {
      "emoji": {
        "emoji": "😼",
        "hexcode": "1F63C",
        "group": "smileys-emotion",
        "subgroups": "cat-face",
        "annotation": "cat with wry smile",
        "tags": "cat, face, ironic, smile, wry",
        "openmoji_tags": "",
        "openmoji_author": "Emily Jäger",
        "openmoji_date": "2018-04-18",
        "skintone": "",
        "skintone_combination": "",
        "skintone_base_emoji": "",
        "skintone_base_hexcode": "",
        "unicode": 0.6,
        "order": 112
      },
      "top": 720,
      "left": 576,
      "index": 108
    },
    {
      "emoji": {
        "emoji": "😽",
        "hexcode": "1F63D",
        "group": "smileys-emotion",
        "subgroups": "cat-face",
        "annotation": "kissing cat",
        "tags": "cat, eye, face, kiss",
        "openmoji_tags": "",
        "openmoji_author": "Emily Jäger",
        "openmoji_date": "2018-04-18",
        "skintone": "",
        "skintone_combination": "",
        "skintone_base_emoji": "",
        "skintone_base_hexcode": "",
        "unicode": 0.6,
        "order": 113
      },
      "top": 720,
      "left": 648,
      "index": 109
    },
    {
      "emoji": {
        "emoji": "🙀",
        "hexcode": "1F640",
        "group": "smileys-emotion",
        "subgroups": "cat-face",
        "annotation": "weary cat",
        "tags": "cat, face, oh, surprised, weary",
        "openmoji_tags": "wow",
        "openmoji_author": "Emily Jäger",
        "openmoji_date": "2018-04-18",
        "skintone": "",
        "skintone_combination": "",
        "skintone_base_emoji": "",
        "skintone_base_hexcode": "",
        "unicode": 0.6,
        "order": 114
      },
      "top": 792,
      "left": 0,
      "index": 110
    },
    {
      "emoji": {
        "emoji": "😿",
        "hexcode": "1F63F",
        "group": "smileys-emotion",
        "subgroups": "cat-face",
        "annotation": "crying cat",
        "tags": "cat, cry, face, sad, tear",
        "openmoji_tags": "unhappy, depressed",
        "openmoji_author": "Emily Jäger",
        "openmoji_date": "2018-04-18",
        "skintone": "",
        "skintone_combination": "",
        "skintone_base_emoji": "",
        "skintone_base_hexcode": "",
        "unicode": 0.6,
        "order": 115
      },
      "top": 792,
      "left": 72,
      "index": 111
    },
    {
      "emoji": {
        "emoji": "😾",
        "hexcode": "1F63E",
        "group": "smileys-emotion",
        "subgroups": "cat-face",
        "annotation": "pouting cat",
        "tags": "cat, face, pouting",
        "openmoji_tags": "sad, angry",
        "openmoji_author": "Emily Jäger",
        "openmoji_date": "2018-04-18",
        "skintone": "",
        "skintone_combination": "",
        "skintone_base_emoji": "",
        "skintone_base_hexcode": "",
        "unicode": 0.6,
        "order": 116
      },
      "top": 792,
      "left": 144,
      "index": 112
    },
    {
      "emoji": {
        "emoji": "🙈",
        "hexcode": "1F648",
        "group": "smileys-emotion",
        "subgroups": "monkey-face",
        "annotation": "see-no-evil monkey",
        "tags": "evil, face, forbidden, monkey, see",
        "openmoji_tags": "",
        "openmoji_author": "Mariella Steeb",
        "openmoji_date": "2018-04-18",
        "skintone": "",
        "skintone_combination": "",
        "skintone_base_emoji": "",
        "skintone_base_hexcode": "",
        "unicode": 0.6,
        "order": 117
      },
      "top": 792,
      "left": 216,
      "index": 113
    },
    {
      "emoji": {
        "emoji": "🙉",
        "hexcode": "1F649",
        "group": "smileys-emotion",
        "subgroups": "monkey-face",
        "annotation": "hear-no-evil monkey",
        "tags": "evil, face, forbidden, hear, monkey",
        "openmoji_tags": "",
        "openmoji_author": "Mariella Steeb",
        "openmoji_date": "2018-04-18",
        "skintone": "",
        "skintone_combination": "",
        "skintone_base_emoji": "",
        "skintone_base_hexcode": "",
        "unicode": 0.6,
        "order": 118
      },
      "top": 792,
      "left": 288,
      "index": 114
    },
    {
      "emoji": {
        "emoji": "🙊",
        "hexcode": "1F64A",
        "group": "smileys-emotion",
        "subgroups": "monkey-face",
        "annotation": "speak-no-evil monkey",
        "tags": "evil, face, forbidden, monkey, speak",
        "openmoji_tags": "",
        "openmoji_author": "Mariella Steeb",
        "openmoji_date": "2018-04-18",
        "skintone": "",
        "skintone_combination": "",
        "skintone_base_emoji": "",
        "skintone_base_hexcode": "",
        "unicode": 0.6,
        "order": 119
      },
      "top": 792,
      "left": 360,
      "index": 115
    },
    {
      "emoji": {
        "emoji": "💋",
        "hexcode": "1F48B",
        "group": "smileys-emotion",
        "subgroups": "emotion",
        "annotation": "kiss mark",
        "tags": "kiss, lips",
        "openmoji_tags": "love",
        "openmoji_author": "Laura Humpfer",
        "openmoji_date": "2018-04-18",
        "skintone": "",
        "skintone_combination": "",
        "skintone_base_emoji": "",
        "skintone_base_hexcode": "",
        "unicode": 0.6,
        "order": 120
      },
      "top": 792,
      "left": 432,
      "index": 116
    },
    {
      "emoji": {
        "emoji": "💌",
        "hexcode": "1F48C",
        "group": "smileys-emotion",
        "subgroups": "emotion",
        "annotation": "love letter",
        "tags": "heart, letter, love, mail",
        "openmoji_tags": "",
        "openmoji_author": "Laura Humpfer",
        "openmoji_date": "2018-04-18",
        "skintone": "",
        "skintone_combination": "",
        "skintone_base_emoji": "",
        "skintone_base_hexcode": "",
        "unicode": 0.6,
        "order": 121
      },
      "top": 792,
      "left": 504,
      "index": 117
    },
    {
      "emoji": {
        "emoji": "💘",
        "hexcode": "1F498",
        "group": "smileys-emotion",
        "subgroups": "emotion",
        "annotation": "heart with arrow",
        "tags": "arrow, cupid",
        "openmoji_tags": "love, inlove",
        "openmoji_author": "Laura Humpfer",
        "openmoji_date": "2018-04-18",
        "skintone": "",
        "skintone_combination": "",
        "skintone_base_emoji": "",
        "skintone_base_hexcode": "",
        "unicode": 0.6,
        "order": 122
      },
      "top": 792,
      "left": 576,
      "index": 118
    },
    {
      "emoji": {
        "emoji": "💝",
        "hexcode": "1F49D",
        "group": "smileys-emotion",
        "subgroups": "emotion",
        "annotation": "heart with ribbon",
        "tags": "ribbon, valentine",
        "openmoji_tags": "present, love",
        "openmoji_author": "Laura Humpfer",
        "openmoji_date": "2018-04-18",
        "skintone": "",
        "skintone_combination": "",
        "skintone_base_emoji": "",
        "skintone_base_hexcode": "",
        "unicode": 0.6,
        "order": 123
      },
      "top": 792,
      "left": 648,
      "index": 119
    },
    {
      "emoji": {
        "emoji": "💖",
        "hexcode": "1F496",
        "group": "smileys-emotion",
        "subgroups": "emotion",
        "annotation": "sparkling heart",
        "tags": "excited, sparkle",
        "openmoji_tags": "love, inlove",
        "openmoji_author": "Laura Humpfer",
        "openmoji_date": "2018-04-18",
        "skintone": "",
        "skintone_combination": "",
        "skintone_base_emoji": "",
        "skintone_base_hexcode": "",
        "unicode": 0.6,
        "order": 124
      },
      "top": 864,
      "left": 0,
      "index": 120
    },
    {
      "emoji": {
        "emoji": "💗",
        "hexcode": "1F497",
        "group": "smileys-emotion",
        "subgroups": "emotion",
        "annotation": "growing heart",
        "tags": "excited, growing, nervous, pulse",
        "openmoji_tags": "love, inlove",
        "openmoji_author": "Laura Humpfer",
        "openmoji_date": "2018-04-18",
        "skintone": "",
        "skintone_combination": "",
        "skintone_base_emoji": "",
        "skintone_base_hexcode": "",
        "unicode": 0.6,
        "order": 125
      },
      "top": 864,
      "left": 72,
      "index": 121
    },
    {
      "emoji": {
        "emoji": "💓",
        "hexcode": "1F493",
        "group": "smileys-emotion",
        "subgroups": "emotion",
        "annotation": "beating heart",
        "tags": "beating, heartbeat, pulsating",
        "openmoji_tags": "love",
        "openmoji_author": "Laura Humpfer",
        "openmoji_date": "2018-04-18",
        "skintone": "",
        "skintone_combination": "",
        "skintone_base_emoji": "",
        "skintone_base_hexcode": "",
        "unicode": 0.6,
        "order": 126
      },
      "top": 864,
      "left": 144,
      "index": 122
    },
    {
      "emoji": {
        "emoji": "💞",
        "hexcode": "1F49E",
        "group": "smileys-emotion",
        "subgroups": "emotion",
        "annotation": "revolving hearts",
        "tags": "revolving",
        "openmoji_tags": "",
        "openmoji_author": "Laura Humpfer",
        "openmoji_date": "2018-04-18",
        "skintone": "",
        "skintone_combination": "",
        "skintone_base_emoji": "",
        "skintone_base_hexcode": "",
        "unicode": 0.6,
        "order": 127
      },
      "top": 864,
      "left": 216,
      "index": 123
    },
    {
      "emoji": {
        "emoji": "💕",
        "hexcode": "1F495",
        "group": "smileys-emotion",
        "subgroups": "emotion",
        "annotation": "two hearts",
        "tags": "love",
        "openmoji_tags": "",
        "openmoji_author": "Laura Humpfer",
        "openmoji_date": "2018-04-18",
        "skintone": "",
        "skintone_combination": "",
        "skintone_base_emoji": "",
        "skintone_base_hexcode": "",
        "unicode": 0.6,
        "order": 128
      },
      "top": 864,
      "left": 288,
      "index": 124
    },
    {
      "emoji": {
        "emoji": "💟",
        "hexcode": "1F49F",
        "group": "smileys-emotion",
        "subgroups": "emotion",
        "annotation": "heart decoration",
        "tags": "heart",
        "openmoji_tags": "",
        "openmoji_author": "Laura Humpfer",
        "openmoji_date": "2018-04-18",
        "skintone": "",
        "skintone_combination": "",
        "skintone_base_emoji": "",
        "skintone_base_hexcode": "",
        "unicode": 0.6,
        "order": 129
      },
      "top": 864,
      "left": 360,
      "index": 125
    },
    {
      "emoji": {
        "emoji": "❣️",
        "hexcode": "2763",
        "group": "smileys-emotion",
        "subgroups": "emotion",
        "annotation": "heart exclamation",
        "tags": "exclamation, mark, punctuation",
        "openmoji_tags": "",
        "openmoji_author": "Laura Humpfer",
        "openmoji_date": "2018-04-18",
        "skintone": "",
        "skintone_combination": "",
        "skintone_base_emoji": "",
        "skintone_base_hexcode": "",
        "unicode": 1,
        "order": 131
      },
      "top": 864,
      "left": 432,
      "index": 126
    },
    {
      "emoji": {
        "emoji": "💔",
        "hexcode": "1F494",
        "group": "smileys-emotion",
        "subgroups": "emotion",
        "annotation": "broken heart",
        "tags": "break, broken",
        "openmoji_tags": "heartbreak",
        "openmoji_author": "Laura Humpfer",
        "openmoji_date": "2018-04-18",
        "skintone": "",
        "skintone_combination": "",
        "skintone_base_emoji": "",
        "skintone_base_hexcode": "",
        "unicode": 0.6,
        "order": 132
      },
      "top": 864,
      "left": 504,
      "index": 127
    },
    {
      "emoji": {
        "emoji": "❤️",
        "hexcode": "2764",
        "group": "smileys-emotion",
        "subgroups": "emotion",
        "annotation": "red heart",
        "tags": "heart",
        "openmoji_tags": "love, red",
        "openmoji_author": "Laura Humpfer",
        "openmoji_date": "2018-04-18",
        "skintone": "",
        "skintone_combination": "",
        "skintone_base_emoji": "",
        "skintone_base_hexcode": "",
        "unicode": 0.6,
        "order": 134
      },
      "top": 864,
      "left": 576,
      "index": 128
    },
    {
      "emoji": {
        "emoji": "🧡",
        "hexcode": "1F9E1",
        "group": "smileys-emotion",
        "subgroups": "emotion",
        "annotation": "orange heart",
        "tags": "orange",
        "openmoji_tags": "",
        "openmoji_author": "Laura Schießer",
        "openmoji_date": "2019-05-06",
        "skintone": "",
        "skintone_combination": "",
        "skintone_base_emoji": "",
        "skintone_base_hexcode": "",
        "unicode": 5,
        "order": 135
      },
      "top": 864,
      "left": 648,
      "index": 129
    },
    {
      "emoji": {
        "emoji": "💛",
        "hexcode": "1F49B",
        "group": "smileys-emotion",
        "subgroups": "emotion",
        "annotation": "yellow heart",
        "tags": "yellow",
        "openmoji_tags": "",
        "openmoji_author": "Laura Humpfer",
        "openmoji_date": "2018-04-18",
        "skintone": "",
        "skintone_combination": "",
        "skintone_base_emoji": "",
        "skintone_base_hexcode": "",
        "unicode": 0.6,
        "order": 136
      },
      "top": 936,
      "left": 0,
      "index": 130
    },
    {
      "emoji": {
        "emoji": "💚",
        "hexcode": "1F49A",
        "group": "smileys-emotion",
        "subgroups": "emotion",
        "annotation": "green heart",
        "tags": "green",
        "openmoji_tags": "",
        "openmoji_author": "Laura Humpfer",
        "openmoji_date": "2018-04-18",
        "skintone": "",
        "skintone_combination": "",
        "skintone_base_emoji": "",
        "skintone_base_hexcode": "",
        "unicode": 0.6,
        "order": 137
      },
      "top": 936,
      "left": 72,
      "index": 131
    },
    {
      "emoji": {
        "emoji": "💙",
        "hexcode": "1F499",
        "group": "smileys-emotion",
        "subgroups": "emotion",
        "annotation": "blue heart",
        "tags": "blue",
        "openmoji_tags": "",
        "openmoji_author": "Laura Humpfer",
        "openmoji_date": "2018-04-18",
        "skintone": "",
        "skintone_combination": "",
        "skintone_base_emoji": "",
        "skintone_base_hexcode": "",
        "unicode": 0.6,
        "order": 138
      },
      "top": 936,
      "left": 144,
      "index": 132
    },
    {
      "emoji": {
        "emoji": "💜",
        "hexcode": "1F49C",
        "group": "smileys-emotion",
        "subgroups": "emotion",
        "annotation": "purple heart",
        "tags": "purple",
        "openmoji_tags": "",
        "openmoji_author": "Laura Humpfer",
        "openmoji_date": "2018-04-18",
        "skintone": "",
        "skintone_combination": "",
        "skintone_base_emoji": "",
        "skintone_base_hexcode": "",
        "unicode": 0.6,
        "order": 139
      },
      "top": 936,
      "left": 216,
      "index": 133
    },
    {
      "emoji": {
        "emoji": "🤎",
        "hexcode": "1F90E",
        "group": "smileys-emotion",
        "subgroups": "emotion",
        "annotation": "brown heart",
        "tags": "brown, heart",
        "openmoji_tags": "",
        "openmoji_author": "Laura Dworatschek",
        "openmoji_date": "2019-05-06",
        "skintone": "",
        "skintone_combination": "",
        "skintone_base_emoji": "",
        "skintone_base_hexcode": "",
        "unicode": 12,
        "order": 140
      },
      "top": 936,
      "left": 288,
      "index": 134
    },
    {
      "emoji": {
        "emoji": "🖤",
        "hexcode": "1F5A4",
        "group": "smileys-emotion",
        "subgroups": "emotion",
        "annotation": "black heart",
        "tags": "black, evil, wicked",
        "openmoji_tags": "",
        "openmoji_author": "Laura Humpfer",
        "openmoji_date": "2018-04-18",
        "skintone": "",
        "skintone_combination": "",
        "skintone_base_emoji": "",
        "skintone_base_hexcode": "",
        "unicode": 3,
        "order": 141
      },
      "top": 936,
      "left": 360,
      "index": 135
    },
    {
      "emoji": {
        "emoji": "🤍",
        "hexcode": "1F90D",
        "group": "smileys-emotion",
        "subgroups": "emotion",
        "annotation": "white heart",
        "tags": "heart, white",
        "openmoji_tags": "",
        "openmoji_author": "Laura Dworatschek",
        "openmoji_date": "2019-05-06",
        "skintone": "",
        "skintone_combination": "",
        "skintone_base_emoji": "",
        "skintone_base_hexcode": "",
        "unicode": 12,
        "order": 142
      },
      "top": 936,
      "left": 432,
      "index": 136
    },
    {
      "emoji": {
        "emoji": "💯",
        "hexcode": "1F4AF",
        "group": "smileys-emotion",
        "subgroups": "emotion",
        "annotation": "hundred points",
        "tags": "100, full, hundred, score",
        "openmoji_tags": "perfect, excellent",
        "openmoji_author": "Jose Avila",
        "openmoji_date": "2018-04-18",
        "skintone": "",
        "skintone_combination": "",
        "skintone_base_emoji": "",
        "skintone_base_hexcode": "",
        "unicode": 0.6,
        "order": 143
      },
      "top": 936,
      "left": 504,
      "index": 137
    },
    {
      "emoji": {
        "emoji": "💢",
        "hexcode": "1F4A2",
        "group": "smileys-emotion",
        "subgroups": "emotion",
        "annotation": "anger symbol",
        "tags": "angry, comic, mad",
        "openmoji_tags": "",
        "openmoji_author": "Anne Frauendorf",
        "openmoji_date": "2018-11-16",
        "skintone": "",
        "skintone_combination": "",
        "skintone_base_emoji": "",
        "skintone_base_hexcode": "",
        "unicode": 0.6,
        "order": 144
      },
      "top": 936,
      "left": 576,
      "index": 138
    },
    {
      "emoji": {
        "emoji": "💥",
        "hexcode": "1F4A5",
        "group": "smileys-emotion",
        "subgroups": "emotion",
        "annotation": "collision",
        "tags": "boom, comic",
        "openmoji_tags": "explosion",
        "openmoji_author": "Laura Humpfer",
        "openmoji_date": "2018-04-18",
        "skintone": "",
        "skintone_combination": "",
        "skintone_base_emoji": "",
        "skintone_base_hexcode": "",
        "unicode": 0.6,
        "order": 145
      },
      "top": 936,
      "left": 648,
      "index": 139
    },
    {
      "emoji": {
        "emoji": "💫",
        "hexcode": "1F4AB",
        "group": "smileys-emotion",
        "subgroups": "emotion",
        "annotation": "dizzy",
        "tags": "comic, star",
        "openmoji_tags": "shootingstar",
        "openmoji_author": "Laura Humpfer",
        "openmoji_date": "2018-04-18",
        "skintone": "",
        "skintone_combination": "",
        "skintone_base_emoji": "",
        "skintone_base_hexcode": "",
        "unicode": 0.6,
        "order": 146
      },
      "top": 1008,
      "left": 0,
      "index": 140
    },
    {
      "emoji": {
        "emoji": "💦",
        "hexcode": "1F4A6",
        "group": "smileys-emotion",
        "subgroups": "emotion",
        "annotation": "sweat droplets",
        "tags": "comic, splashing, sweat",
        "openmoji_tags": "",
        "openmoji_author": "Laura Humpfer",
        "openmoji_date": "2018-04-18",
        "skintone": "",
        "skintone_combination": "",
        "skintone_base_emoji": "",
        "skintone_base_hexcode": "",
        "unicode": 0.6,
        "order": 147
      },
      "top": 1008,
      "left": 72,
      "index": 141
    },
    {
      "emoji": {
        "emoji": "💨",
        "hexcode": "1F4A8",
        "group": "smileys-emotion",
        "subgroups": "emotion",
        "annotation": "dashing away",
        "tags": "comic, dash, running",
        "openmoji_tags": "",
        "openmoji_author": "Laura Humpfer",
        "openmoji_date": "2018-04-18",
        "skintone": "",
        "skintone_combination": "",
        "skintone_base_emoji": "",
        "skintone_base_hexcode": "",
        "unicode": 0.6,
        "order": 148
      },
      "top": 1008,
      "left": 144,
      "index": 142
    },
    {
      "emoji": {
        "emoji": "🕳️",
        "hexcode": "1F573",
        "group": "smileys-emotion",
        "subgroups": "emotion",
        "annotation": "hole",
        "tags": "hole",
        "openmoji_tags": "",
        "openmoji_author": "Laura Humpfer",
        "openmoji_date": "2018-04-18",
        "skintone": "",
        "skintone_combination": "",
        "skintone_base_emoji": "",
        "skintone_base_hexcode": "",
        "unicode": 0.7,
        "order": 150
      },
      "top": 1008,
      "left": 216,
      "index": 143
    },
    {
      "emoji": {
        "emoji": "💣️",
        "hexcode": "1F4A3",
        "group": "smileys-emotion",
        "subgroups": "emotion",
        "annotation": "bomb",
        "tags": "comic",
        "openmoji_tags": "explosion",
        "openmoji_author": "Laura Humpfer",
        "openmoji_date": "2018-04-18",
        "skintone": "",
        "skintone_combination": "",
        "skintone_base_emoji": "",
        "skintone_base_hexcode": "",
        "unicode": 0.6,
        "order": 151
      },
      "top": 1008,
      "left": 288,
      "index": 144
    },
    {
      "emoji": {
        "emoji": "💬",
        "hexcode": "1F4AC",
        "group": "smileys-emotion",
        "subgroups": "emotion",
        "annotation": "speech balloon",
        "tags": "balloon, bubble, comic, dialog, speech",
        "openmoji_tags": "talk",
        "openmoji_author": "Laura Humpfer",
        "openmoji_date": "2018-04-18",
        "skintone": "",
        "skintone_combination": "",
        "skintone_base_emoji": "",
        "skintone_base_hexcode": "",
        "unicode": 0.6,
        "order": 152
      },
      "top": 1008,
      "left": 360,
      "index": 145
    },
    {
      "emoji": {
        "emoji": "🗨️",
        "hexcode": "1F5E8",
        "group": "smileys-emotion",
        "subgroups": "emotion",
        "annotation": "left speech bubble",
        "tags": "dialog, speech",
        "openmoji_tags": "",
        "openmoji_author": "Laura Humpfer",
        "openmoji_date": "2018-04-18",
        "skintone": "",
        "skintone_combination": "",
        "skintone_base_emoji": "",
        "skintone_base_hexcode": "",
        "unicode": 2,
        "order": 158
      },
      "top": 1008,
      "left": 432,
      "index": 146
    },
    {
      "emoji": {
        "emoji": "🗯️",
        "hexcode": "1F5EF",
        "group": "smileys-emotion",
        "subgroups": "emotion",
        "annotation": "right anger bubble",
        "tags": "angry, balloon, bubble, mad",
        "openmoji_tags": "",
        "openmoji_author": "Laura Humpfer",
        "openmoji_date": "2018-04-18",
        "skintone": "",
        "skintone_combination": "",
        "skintone_base_emoji": "",
        "skintone_base_hexcode": "",
        "unicode": 0.7,
        "order": 160
      },
      "top": 1008,
      "left": 504,
      "index": 147
    },
    {
      "emoji": {
        "emoji": "💭",
        "hexcode": "1F4AD",
        "group": "smileys-emotion",
        "subgroups": "emotion",
        "annotation": "thought balloon",
        "tags": "balloon, bubble, comic, thought",
        "openmoji_tags": "think",
        "openmoji_author": "Laura Humpfer",
        "openmoji_date": "2018-04-18",
        "skintone": "",
        "skintone_combination": "",
        "skintone_base_emoji": "",
        "skintone_base_hexcode": "",
        "unicode": 1,
        "order": 161
      },
      "top": 1008,
      "left": 576,
      "index": 148
    },
    {
      "emoji": {
        "emoji": "💤",
        "hexcode": "1F4A4",
        "group": "smileys-emotion",
        "subgroups": "emotion",
        "annotation": "zzz",
        "tags": "comic, sleep",
        "openmoji_tags": "night",
        "openmoji_author": "Laura Humpfer",
        "openmoji_date": "2018-04-18",
        "skintone": "",
        "skintone_combination": "",
        "skintone_base_emoji": "",
        "skintone_base_hexcode": "",
        "unicode": 0.6,
        "order": 162
      },
      "top": 1008,
      "left": 648,
      "index": 149
    }
  ]
}